Workbook
Name ApprovedSnapshotStatus: Checks!$C$6
Name BaseValuePerShare: DCF!$M$26
Name BasicShares: Sources!$N$22
Name BearValuePerShare: DCF!$L$26
Name BullValuePerShare: DCF!$N$26
Name CalculatedWACC: WACC!$E$36
Name CarryingDebt: Sources!$D$16
Name CarryingDebtWACC: WACC!$J$36
Name CashAndShortTermInvestments: Sources!$N$24
Name ClassAShares: Sources!$D$10
Name ClassBShares: Sources!$D$11
Name DebtDefaultSpread: Sources!$D$21
Name DilutedProxyShares: Sources!$N$23
Name EquityRiskPremium: Sources!$D$20
Name FairValueDebt: Sources!$D$15
Name IncrementalDilutiveShares: Sources!$D$12
Name InformationCutoff: Sources!$N$14
Name MechanicalIntegrityStatus: Checks!$A$6
Name ModelDate: Sources!$D$7
Name ModelStatus: Checks!$H$6
Name OperatingLeaseLiabilitiesMemo: Sources!$D$18
Name OperatingTaxRate: Sources!$D$22
Name PackageBuildControlStatus: Checks!$G$6
Name RedeemablePreferredStock: Sources!$D$17
Name ReferenceMarketDate: Sources!$D$8
Name ReferenceMarketPrice: Sources!$D$9
Name RiskFreeRate: Sources!$D$19
Name ScenarioList: Sources!$N$7:$N$9
Name SelectedEnterpriseValue: DCF!$E$52
Name SelectedEquityValue: DCF!$E$57
Name SelectedScenario: Cover!$D$6
Name SelectedTerminalValueShare: DCF!$E$63
Name SelectedValuePerShare: DCF!$E$59
Name SensitivityCenter: Sensitivity!$F$11
Name TerminalGrowth: Sources!$D$30
Name WarningStatus: Checks!$E$6

Sheet Cover
B2: Nike valuation model
B3: Independent portfolio analysis based on reconciled SEC-derived history and approved analyst scenarios
B6: Selected scenario | D6: Base
B8: DCF valuation date | D8: =ModelDate -> 46269
B9: Information cutoff | D9: =InformationCutoff -> 46272
B10: Reference market date | D10: =ReferenceMarketDate -> 46269
B13: Illustrative value comparison
B14: Case | D14: Value per share
B15: Bear | D15: =BearValuePerShare -> 30.057414
B16: Base | D16: =BaseValuePerShare -> 47.80676
B17: Bull | D17: =BullValuePerShare -> 59.547617
B18: Reference price | D18: =ReferenceMarketPrice -> 38.4
B21: Selected-scenario outputs
B22: Enterprise value | D22: =SelectedEnterpriseValue -> 69893.935
B23: Equity value | D23: =SelectedEquityValue -> 70978.635
B24: Illustrative value per share | D24: =SelectedValuePerShare -> 47.80676
B25: Calculated WACC | D25: =CalculatedWACC -> 0.084874438
B26: Terminal growth | D26: =TerminalGrowth -> 0.025
B27: PV terminal value / enterprise value | D27: =SelectedTerminalValueShare -> 0.78207976
B28: Canonical publication status | D28: =ModelStatus -> PASS WITH WARNINGS
B31: Navigation
B32: Sources
B33: Historical
B34: Scenarios
B35: WACC
B36: DCF
B37: Sensitivity
B38: Checks
B41: Annual-model approximation: FY2027 FCFF covers the full fiscal year; Sep. 4 is the discount anchor, while equity-bridge balances remain at May 31. Checks separate mechanical integrity from reconciliation to the approved snapshot. This is not an investment recommendation or price target.
B44: Formatting legend
B45: Editable assumption or control
B46: Same-sheet formula
B47: Internal cross-sheet reference

Sheet Sources
B2: Sources and assumptions
B3: Embedded local inputs; no external workbook links or live data connections
A6: Assumption Id | B6: Category | C6: Input Name | D6: Value | E6: Unit | F6: Observation Date | G6: Source Ids | H6: Source Type | I6: Owner Status | J6: Notes | M6: Scenario selector values
A7: VA01 | B7: model_timing | C7: model_date | D7: 46269 | E7: date | F7: 46269 | G7: VS04;VS09 | H7: approved_methodology | I7: approved | J7: DCF valuation and discount-anchor date aligned with the reference market date. | N7: Bear
A8: VA02 | B8: market | C8: reference_market_date | D8: 46269 | E8: date | F8: 46269 | G8: VS04;VS05;VS09 | H8: reported_market_input | I8: approved | J8: Reference market date and DCF valuation date; the latest reported balance sheet remains May 31 2026. | N8: Base
A9: VA03 | B9: market | C9: reference_market_price | D9: 38.4 | E9: USD per share | F9: 46269 | G9: VS05 | H9: reported_market_input | I9: approved | J9: NKE Class B closing price. | N9: Bull
A10: VA04 | B10: shares | C10: class_a_shares_outstanding | D10: 281.38775 | E10: millions | F10: 46211 | G10: VS02 | H10: reported_filing_input | I10: approved | J10: Economically participates with Class B and converts one-for-one.
A11: VA05 | B11: shares | C11: class_b_shares_outstanding | D11: 1202.111 | E11: millions | F11: 46211 | G11: VS02 | H11: reported_filing_input | I11: approved | J11: NKE publicly traded share class.
A12: VA06 | B12: shares | C12: incremental_dilutive_share_proxy | D12: 1.2 | E12: millions | F12: 46173 | G12: VS02;VS09 | H12: reported_proxy | I12: approved | J12: FY2026 weighted-average incremental dilutive awards; not a point-in-time treasury-stock calculation. | M12: Workbook metadata
A13: VA07 | B13: equity_bridge | C13: cash_and_cash_equivalents | D13: 7563 | E13: USD millions | F13: 46173 | G13: VS01;VS02 | H13: reported_filing_input | I13: approved | J13: Added because FCFF values operating assets and excludes interest income. | M13: DCF valuation date | N13: 46269
A14: VA08 | B14: equity_bridge | C14: short_term_investments | D14: 1464 | E14: USD millions | F14: 46173 | G14: VS01;VS02 | H14: reported_filing_input | I14: approved | J14: Added with cash; no unsupported minimum-cash deduction. | M14: Information cutoff | N14: 46272
A15: VA09 | B15: debt | C15: fair_value_debt | D15: 6800 | E15: USD millions | F15: 46173 | G15: VS02;VS09 | H15: reported_filing_input | I15: approved | J15: Approximate disclosed fair value used for primary WACC capital weighting. | M15: Reference market date | N15: 46269
A16: VA10 | B16: debt | C16: carrying_interest_bearing_debt | D16: 7942 | E16: USD millions | F16: 46173 | G16: VS01;VS02;VS09 | H16: reported_filing_input | I16: approved | J16: Used in the primary enterprise-to-equity bridge and WACC cross-check. | M16: Valuation inputs | N16: config/valuation_assumptions.csv
A17: VA11 | B17: equity_bridge | C17: redeemable_preferred_stock | D17: 0.3 | E17: USD millions | F17: 46173 | G17: VS02;VS09 | H17: reported_filing_input | I17: approved | J17: Explicit bridge deduction even though it rounds to zero in whole USD millions. | M17: Scenario assumptions | N17: config/scenario_assumptions.csv
A18: VA12 | B18: memorandum | C18: operating_lease_liabilities | D18: 3091 | E18: USD millions | F18: 46173 | G18: VS01;VS02;VS09 | H18: reported_filing_input | I18: approved | J18: Shown separately and not deducted under the approved operating lease convention. | M18: Python valuation results | N18: outputs/model_exports/valuation_summary.csv
A19: VA13 | B19: wacc | C19: risk_free_rate | D19: 0.0478 | E19: decimal | F19: 46269 | G19: VS03 | H19: reported_market_input | I19: approved | J19: Ten-year nominal Treasury constant-maturity rate.
A20: VA14 | B20: wacc | C20: equity_risk_premium | D20: 0.0414 | E20: decimal | F20: 46266 | G20: VS06 | H20: reported_market_input | I20: approved | J20: Implied US ERP using an unadjusted Treasury risk-free convention.
A21: VA15 | B21: wacc | C21: debt_default_spread | D21: 0.0078 | E21: decimal | F21: 46023 | G21: VS02;VS08 | H21: market_proxy | I21: approved | J21: Conservative A2/A spread for Nike's A+ and A2 disclosed ratings. | M21: Calculated input combinations
A22: VA16 | B22: wacc | C22: operating_tax_rate | D22: 0.21 | E22: decimal | F22: 46173 | G22: VS01;VS09 | H22: approved_methodology | I22: approved | J22: Approved Phase 4 normalized operating tax rate. | M22: Basic shares | N22: =ClassAShares+ClassBShares -> 1483.4987
A23: VA17 | B23: bottom_up_beta | C23: footwear_revenue | D23: 30538 | E23: USD millions | F23: 46173 | G23: VS02 | H23: reported_filing_input | I23: approved | J23: Nike Brand and Converse footwear revenue. | M23: Diluted proxy shares | N23: =BasicShares+IncrementalDilutiveShares -> 1484.6987
A24: VA18 | B24: bottom_up_beta | C24: apparel_revenue | D24: 13497 | E24: USD millions | F24: 46173 | G24: VS02 | H24: reported_filing_input | I24: approved | J24: Nike Brand and Converse apparel revenue. | M24: Cash and short-term investments | N24: =Sources!D13+Sources!D14 -> 9027
A25: VA19 | B25: bottom_up_beta | C25: equipment_revenue | D25: 2220 | E25: USD millions | F25: 46173 | G25: VS02 | H25: reported_filing_input | I25: approved | J25: Nike Brand and Converse equipment revenue.
A26: VA20 | B26: bottom_up_beta | C26: other_revenue | D26: 143 | E26: USD millions | F26: 46173 | G26: VS02 | H26: reported_filing_input | I26: approved | J26: Licensing; Converse other; and corporate residual reconciles product categories to revenue.
A27: VA21 | B27: bottom_up_beta | C27: footwear_unlevered_beta | D27: 1 | E27: decimal | F27: 46023 | G27: VS07 | H27: market_proxy | I27: approved | J27: Damodaran cash-corrected Shoe sector unlevered beta.
A28: VA22 | B28: bottom_up_beta | C28: apparel_unlevered_beta | D28: 0.79 | E28: decimal | F28: 46023 | G28: VS07 | H28: market_proxy | I28: approved | J28: Damodaran cash-corrected Apparel sector unlevered beta.
A29: VA23 | B29: bottom_up_beta | C29: equipment_unlevered_beta | D29: 0.74 | E29: decimal | F29: 46023 | G29: VS07 | H29: market_proxy | I29: approved | J29: Damodaran cash-corrected Recreation sector unlevered beta.
A30: VA24 | B30: terminal_value | C30: terminal_growth_rate | D30: 0.025 | E30: decimal | F30: 46272 | G30: VS09;VS10;VS11 | H30: approved_methodology | I30: approved | J30: Common perpetual growth rate for Bear; Base; and Bull headline valuations.
A31: VA25 | B31: sensitivity | C31: sensitivity_wacc_delta_minus_100bp | D31: -0.01 | E31: decimal | F31: 46272 | G31: VS09 | H31: approved_methodology | I31: approved | J31: Applied to the exact formula-derived WACC.
A32: VA26 | B32: sensitivity | C32: sensitivity_wacc_delta_minus_50bp | D32: -0.005 | E32: decimal | F32: 46272 | G32: VS09 | H32: approved_methodology | I32: approved | J32: Applied to the exact formula-derived WACC.
A33: VA27 | B33: sensitivity | C33: sensitivity_wacc_delta_center | D33: 0 | E33: decimal | F33: 46272 | G33: VS09 | H33: approved_methodology | I33: approved | J33: Center row equals the exact formula-derived WACC.
A34: VA28 | B34: sensitivity | C34: sensitivity_wacc_delta_plus_50bp | D34: 0.005 | E34: decimal | F34: 46272 | G34: VS09 | H34: approved_methodology | I34: approved | J34: Applied to the exact formula-derived WACC.
A35: VA29 | B35: sensitivity | C35: sensitivity_wacc_delta_plus_100bp | D35: 0.01 | E35: decimal | F35: 46272 | G35: VS09 | H35: approved_methodology | I35: approved | J35: Applied to the exact formula-derived WACC.
A36: VA30 | B36: sensitivity | C36: sensitivity_terminal_growth_150bp | D36: 0.015 | E36: decimal | F36: 46272 | G36: VS09 | H36: approved_methodology | I36: approved | J36: Direct-growth sensitivity column.
... A40: VA34 | B40: sensitivity | C40: sensitivity_terminal_growth_350bp | D40: 0.035 | E40: decimal | F40: 46272 | G40: VS09 | H40: approved_methodology | I40: approved | J40: Direct-growth sensitivity column.
A44: Source Id | B44: Category | C44: Title | D44: Publisher | E44: Source Type | F44: Publication Date | G44: Observation Date | H44: Information Cutoff | I44: Url Or Accession | J44: Fields Supported | K44: Retrieval Date | L44: Notes
A45: VS01 | B45: project_data | C45: Committed Phase 4 scenario forecast | D45: Independent project | E45: committed_project_data | F45: 46273 | G45: 46173 | H45: 46272 | I45: outputs/tables/scenario_forecast_long.csv | J45: FY2027-FY2031 operating forecasts and FCFF | K45: 46273 | L45: Protected full-precision project output; no network access required.
A46: VS02 | B46: company_filing | C46: Fiscal 2026 Form 10-K | D46: NIKE Inc. | E46: official_sec_filing | F46: 46218 | G46: 46173 | H46: 46272 | I46: https://www.sec.gov/Archives/edgar/data/320187/000032018726000088/nke-20260531.htm | J46: Shares; product revenue; cash; investments; debt; leases; preferred stock; ratings; and awards | K46: 46273 | L46: Share count observation is July 8 2026 where specifically noted.
A47: VS03 | B47: market_rate | C47: Daily Treasury par yield curve rates | D47: U.S. Department of the Treasury | E47: official_government_data | F47: 46269 | G47: 46269 | H47: 46272 | I47: https://home.treasury.gov/resource-center/data-chart-center/interest-rates/TextView?field_tdr_date_value=2026&type=daily_treasury_yield_curve | J47: Ten-year nominal Treasury constant-maturity rate | K47: 46273 | L47: September 4 2026 ten-year rate is 4.78%.
A48: VS04 | B48: market_calendar | C48: Holidays and trading hours | D48: New York Stock Exchange | E48: official_exchange_calendar | F48: 46023 | G48: 46272 | H48: 46272 | I48: https://www.nyse.com/trade/hours-calendars | J48: September 7 2026 market holiday and September 4 valuation date | K48: 46273 | L48: Establishes September 4 as the last trading date before the cutoff and the DCF discount anchor.
A49: VS05 | B49: market_price | C49: Nike Inc. Cl B historical prices | D49: The Wall Street Journal | E49: reputable_historical_price | F49: 46269 | G49: 46269 | H49: 46272 | I49: https://www.wsj.com/market-data/quotes/NKE/historical-prices | J49: NKE September 4 2026 closing price | K49: 46273 | L49: Closing price is USD 38.40; reference comparison only.
A50: VS06 | B50: equity_risk | C50: Implied equity risk premium update | D50: Aswath Damodaran / NYU Stern | E50: valuation_dataset | F50: 46266 | G50: 46266 | H50: 46272 | I50: https://pages.stern.nyu.edu/~adamodar/New_Home_Page/home.htm | J50: Implied US equity risk premium | K50: 46273 | L50: Trailing-twelve-month adjusted-payout ERP is 4.14% using an unadjusted Treasury rate.
A51: VS07 | B51: bottom_up_beta | C51: Betas by sector US | D51: Aswath Damodaran / NYU Stern | E51: valuation_dataset | F51: 46023 | G51: 46023 | H51: 46272 | I51: https://pages.stern.nyu.edu/~adamodar/New_Home_Page/datafile/Betas.html | J51: Cash-corrected unlevered betas for Shoe; Apparel; and Recreation | K51: 46273 | L51: Used with Nike's disclosed FY2026 product mix.
A52: VS08 | B52: debt_spread | C52: Ratings interest coverage ratios and default spreads | D52: Aswath Damodaran / NYU Stern | E52: valuation_dataset | F52: 46023 | G52: 46023 | H52: 46272 | I52: https://pages.stern.nyu.edu/~adamodar/New_Home_Page/datafile/ratings.html | J52: A2/A default spread | K52: 46273 | L52: 0.78% spread added to the nominal risk-free rate.
A53: VS09 | B53: owner_decision | C53: Phase 5A valuation methodology approval | D53: Project owner | E53: owner_decision | G53: 46273 | H53: 46272 | I53: docs/decision_log.md | J53: Timing; WACC; terminal growth; equity bridge; dilution; and sensitivity decisions | K53: 46273 | L53: Owner decision date does not introduce post-cutoff company or market information.
A54: VS10 | B54: calculation_method | C54: XNPV function | D54: Microsoft | E54: official_software_documentation | G54: 46272 | H54: 46272 | I54: https://support.microsoft.com/en-us/excel/functions/xnpv-function | J54: Exact date discounting using a 365-day convention | K54: 46273 | L54: Python reproduces the same explicit date-exponent method without invoking Excel.
A55: VS11 | B55: terminal_context | C55: Longer-run inflation and real potential growth context | D55: Federal Reserve and Congressional Budget Office | E55: official_government_context | F55: 46054 | G55: 46272 | H55: 46272 | I55: https://www.federalreserve.gov/faqs/economy_14400.htm; https://www.cbo.gov/publication/62105 | J55: Reasonableness context for 2.5% perpetual growth | K55: 46273 | L55: Terminal growth remains below the approximate long-run nominal economic-growth anchor.
A59: Scenario | B59: Fiscal Year | C59: Driver | D59: Value | E59: Unit | F59: Historical Anchor | G59: Rationale | H59: Source Id | I59: Source Type | J59: Owner Status | K59: Notes
A60: base | B60: FY2027 | C60: revenue_growth | D60: -0.02 | E60: decimal | F60: FY2026 revenue USD 46398m and 0.2% growth | G60: Near-term pressure followed by partial second-half improvement | H60: FS04 | I60: analyst_assumption | J60: approved | K60: deterioration
A61: base | B61: FY2027 | C61: gross_margin | D61: 0.425 | E61: decimal | F61: FY2026 reported 42.9% | G61: Modest decline from reported margin while underlying operations begin to recover | H61: FS03 | I61: analyst_assumption | J61: approved | K61: deterioration
A62: base | B62: FY2027 | C62: sga_percent_revenue | D62: 0.352 | E62: decimal | F62: FY2026 34.7% | G62: Cost rigidity and investment raise the ratio on lower revenue | H62: FS04 | I62: analyst_assumption | J62: approved | K62: deterioration
A63: base | B63: FY2027 | C63: normalized_tax_rate | D63: 0.21 | E63: decimal | F63: FY2026 20.3% and FY2027 low-20% outlook | G63: Transparent normalized operating tax rate | H63: FS04 | I63: analyst_assumption | J63: approved | K63: constant across scenarios
A64: base | B64: FY2027 | C64: da_percent_revenue | D64: 0.016 | E64: decimal | F64: Five-year median 1.55% | G64: Rounded stable historical anchor | H64: FS01 | I64: analyst_assumption | J64: approved | K64: stabilization
A65: base | B65: FY2027 | C65: capex_percent_revenue | D65: 0.015 | E65: decimal | F65: Five-year average 1.50% | G65: Maintains reinvestment during near-term pressure | H65: FS01 | I65: analyst_assumption | J65: approved | K65: stabilization
A66: base | B66: FY2027 | C66: operating_nwc_percent_revenue | D66: 0.111 | E66: decimal | F66: FY2026 11.87% including tariff receivable | G66: Partial normalization without separately adding subsequent collection | H66: FS03 | I66: analyst_assumption | J66: approved | K66: normalization
A67: base | B67: FY2028 | C67: revenue_growth | D67: 0.02 | E67: decimal | F67: FY2022-FY2026 growth range -9.8% to 9.6% | G67: Measured recovery after FY2027 pressure | H67: FS04 | I67: analyst_assumption | J67: approved | K67: stabilization
A68: base | B68: FY2028 | C68: gross_margin | D68: 0.432 | E68: decimal | F68: Five-year median 43.52% | G68: Gradual improvement without returning immediately to peak | H68: FS03 | I68: analyst_assumption | J68: approved | K68: recovery
A69: base | B69: FY2028 | C69: sga_percent_revenue | D69: 0.345 | E69: decimal | F69: Three-year median 34.73% | G69: Early operating leverage as revenue stabilizes | H69: FS04 | I69: analyst_assumption | J69: approved | K69: recovery
A70: base | B70: FY2028 | C70: normalized_tax_rate | D70: 0.21 | E70: decimal | F70: FY2027 low-20% company outlook | G70: No unsupported scenario tax mix | H70: FS04 | I70: analyst_assumption | J70: approved | K70: constant across scenarios
A71: base | B71: FY2028 | C71: da_percent_revenue | D71: 0.016 | E71: decimal | F71: Three-year average 1.61% | G71: Stable asset-consumption proxy | H71: FS01 | I71: analyst_assumption | J71: approved | K71: stabilization
... A164: bear | B164: FY2031 | C164: operating_nwc_percent_revenue | D164: 0.115 | E164: decimal | F164: Historical range 8.97%-11.87% | G164: Remains near historical high | H164: FS01 | I164: analyst_assumption | J164: approved | K164: mature-state convergence

Sheet Historical
B2: Historical DCF inputs
B3: FY2022A-FY2026A; USD millions except per-share, share-count, and percentage lines
B7: Metric | C7: Unit | D7: FY2022A | E7: FY2023A | F7: FY2024A | G7: FY2025A | H7: FY2026A | I7: Source / convention
B8: Revenue | C8: USD millions | D8: 46710 | E8: 51217 | F8: 51362 | G8: 46309 | H8: 46398 | I8: Committed Phase 4 actual bridge.
B9: Derived operating income | C9: USD millions | D9: 6675 | E9: 5915 | F9: 6311 | G9: 3702 | H9: 3797 | I9: Project-derived consolidated subtotal: gross profit less total SG&A; not Nike-reported or segment EBIT.
B10: Derived operating margin | C10: decimal | D10: 0.142903 | E10: 0.115489 | F10: 0.122873 | G10: 0.079941 | H10: 0.081835 | I10: Committed Phase 4 actual bridge.
B11: Historical effective operating tax rate | C11: decimal | D11: 0.090963765 | E11: 0.18238994 | F11: 0.14925373 | G11: 0.17142857 | H11: 0.20307692 | I11: Committed Phase 4 actual bridge.
B12: Depreciation and amortization | C12: USD millions | D12: 717 | E12: 703 | F12: 796 | G12: 775 | H12: 747 | I12: Committed Phase 4 actual bridge.
B13: Capital expenditures | C13: USD millions | D13: 758 | E13: 969 | F13: 812 | G13: 430 | H13: 684 | I13: Positive amount represents investment spending.
B14: Operating NWC proxy | C14: USD millions | D14: 5416 | E14: 5702 | F14: 4690 | G14: 4152 | H14: 5507 | I14: Committed Phase 4 actual bridge.
B15: Change in operating NWC | C15: USD millions | E15: 286 | F15: -1012 | G15: -538 | H15: 1355 | I15: FY2022 is not applicable because FY2021 opening operating NWC is unavailable.
B16: Historical FCFF | C16: USD millions | E16: 4284.1635 | F16: 6365.0597 | G16: 3950.3714 | H16: 1733.9169 | I16: FY2022 is not applicable because FY2021 opening operating NWC is unavailable.
B20: FY2026 valuation bridge and share inputs
B22: Cash and cash equivalents | C22: USD millions | H22: =Sources!D13 -> 7563 | I22: VS01;VS02
B23: Short-term investments | C23: USD millions | H23: =Sources!D14 -> 1464 | I23: VS01;VS02
B24: Carrying interest-bearing debt | C24: USD millions | H24: =CarryingDebt -> 7942 | I24: VS01;VS02;VS09
B25: Operating leases (memorandum) | C25: USD millions | H25: =OperatingLeaseLiabilitiesMemo -> 3091 | I25: VS01;VS02;VS09
B26: Class A shares outstanding | C26: millions | H26: =ClassAShares -> 281.38775 | I26: VS02
B27: Class B shares outstanding | C27: millions | H27: =ClassBShares -> 1202.111 | I27: VS02
B28: Incremental dilutive-share proxy | C28: millions | H28: =IncrementalDilutiveShares -> 1.2 | I28: VS02;VS09
B29: Basic shares | C29: millions | H29: =BasicShares -> 1483.4987 | I29: VA04;VA05
B30: Diluted proxy shares | C30: millions | H30: =DilutedProxyShares -> 1484.6987 | I30: VA04;VA05;VA06

Sheet Scenarios
B2: Operating scenarios
B3: FY2026A anchor and approved FY2027E-FY2031E analyst scenarios; USD millions unless noted
B7: Bear scenario
B8: Metric | C8: Unit | D8: FY2026A | E8: FY2027E | F8: FY2028E | G8: FY2029E | H8: FY2030E | I8: FY2031E | J8: Source / formula
B9: Revenue growth | C9: decimal | D9: 0.001922 | E9: =Sources!$D$130 -> -0.04 | F9: =Sources!$D$137 -> -0.01 | G9: =Sources!$D$144 -> 0.01 | H9: =Sources!$D$151 -> 0.02 | I9: =Sources!$D$158 -> 0.02 | J9: Approved scenario driver linked from Sources.
B10: Revenue | C10: USD millions | D10: 46398 | E10: =D10*(1+E9) -> 44542.08 | F10: =E10*(1+F9) -> 44096.659 | G10: =F10*(1+G9) -> 44537.626 | H10: =G10*(1+H9) -> 45428.378 | I10: =H10*(1+I9) -> 46336.946 | J10: Native workbook formula.
B11: Gross margin | C11: decimal | D11: 0.429135 | E11: =Sources!$D$131 -> 0.415 | F11: =Sources!$D$138 -> 0.415 | G11: =Sources!$D$145 -> 0.42 | H11: =Sources!$D$152 -> 0.425 | I11: =Sources!$D$159 -> 0.428 | J11: Approved scenario driver linked from Sources.
B12: Gross profit | C12: USD millions | D12: 19911 | E12: =E10*E11 -> 18484.963 | F12: =F10*F11 -> 18300.114 | G12: =G10*G11 -> 18705.803 | H12: =H10*H11 -> 19307.061 | I12: =I10*I11 -> 19832.213 | J12: Native workbook formula.
B13: SG&A / revenue | C13: decimal | D13: 0.34729945 | E13: =Sources!$D$132 -> 0.355 | F13: =Sources!$D$139 -> 0.357 | G13: =Sources!$D$146 -> 0.354 | H13: =Sources!$D$153 -> 0.35 | I13: =Sources!$D$160 -> 0.346 | J13: Approved scenario driver linked from Sources.
B14: Total SG&A | C14: USD millions | D14: 16114 | E14: =E10*E13 -> 15812.438 | F14: =F10*F13 -> 15742.507 | G14: =G10*G13 -> 15766.32 | H14: =H10*H13 -> 15899.932 | I14: =I10*I13 -> 16032.583 | J14: Native workbook formula.
B15: Derived operating income | C15: USD millions | D15: 3797 | E15: =E12-E14 -> 2672.5248 | F15: =F12-F14 -> 2557.6062 | G15: =G12-G14 -> 2939.4833 | H15: =H12-H14 -> 3407.1284 | I15: =I12-I14 -> 3799.6296 | J15: Gross profit less total SG&A; not Nike-reported or segment EBIT.
B16: Derived operating margin | C16: decimal | D16: 0.081835 | E16: =E15/E10 -> 0.06 | F16: =F15/F10 -> 0.058 | G16: =G15/G10 -> 0.066 | H16: =H15/H10 -> 0.075 | I16: =I15/I10 -> 0.082 | J16: Native workbook formula.
B17: Operating tax rate | C17: decimal | D17: 0.20307692 | E17: =Sources!$D$133 -> 0.21 | F17: =Sources!$D$140 -> 0.21 | G17: =Sources!$D$147 -> 0.21 | H17: =Sources!$D$154 -> 0.21 | I17: =Sources!$D$161 -> 0.21 | J17: Approved scenario driver linked from Sources.
B18: Normalized operating tax expense | C18: USD millions | D18: 771.08308 | E18: =MAX(E15,0)*E17 -> 561.23021 | F18: =MAX(F15,0)*F17 -> 537.09731 | G18: =MAX(G15,0)*G17 -> 617.29149 | H18: =MAX(H15,0)*H17 -> 715.49696 | I18: =MAX(I15,0)*I17 -> 797.92221 | J18: Native workbook formula.
B19: NOPAT | C19: USD millions | D19: 3025.9169 | E19: =E15-E18 -> 2111.2946 | F19: =F15-F18 -> 2020.5089 | G19: =G15-G18 -> 2322.1918 | H19: =H15-H18 -> 2691.6314 | I19: =I15-I18 -> 3001.7074 | J19: Native workbook formula.
B20: D&A / revenue | C20: decimal | D20: 0.016099832 | E20: =Sources!$D$134 -> 0.016 | F20: =Sources!$D$141 -> 0.016 | G20: =Sources!$D$148 -> 0.016 | H20: =Sources!$D$155 -> 0.015 | I20: =Sources!$D$162 -> 0.015 | J20: Approved scenario driver linked from Sources.
B21: Depreciation and amortization | C21: USD millions | D21: 747 | E21: =E10*E20 -> 712.67328 | F21: =F10*F20 -> 705.54655 | G21: =G10*G20 -> 712.60201 | H21: =H10*H20 -> 681.42567 | I21: =I10*I20 -> 695.05419 | J21: Native workbook formula.
B22: Capex / revenue | C22: decimal | D22: 0.014742015 | E22: =Sources!$D$135 -> 0.013 | F22: =Sources!$D$142 -> 0.013 | G22: =Sources!$D$149 -> 0.014 | H22: =Sources!$D$156 -> 0.015 | I22: =Sources!$D$163 -> 0.015 | J22: Approved scenario driver linked from Sources.
B23: Capital expenditures | C23: USD millions | D23: 684 | E23: =E10*E22 -> 579.04704 | F23: =F10*F22 -> 573.25657 | G23: =G10*G22 -> 623.52676 | H23: =H10*H22 -> 681.42567 | I23: =I10*I22 -> 695.05419 | J23: Native workbook formula.
B24: Operating NWC / revenue | C24: decimal | D24: 0.11869046 | E24: =Sources!$D$136 -> 0.117 | F24: =Sources!$D$143 -> 0.118 | G24: =Sources!$D$150 -> 0.118 | H24: =Sources!$D$157 -> 0.117 | I24: =Sources!$D$164 -> 0.115 | J24: Approved scenario driver linked from Sources.
B25: Operating NWC proxy | C25: USD millions | D25: 5507 | E25: =E10*E24 -> 5211.4234 | F25: =F10*F24 -> 5203.4058 | G25: =G10*G24 -> 5255.4398 | H25: =H10*H24 -> 5315.1203 | I25: =I10*I24 -> 5328.7488 | J25: Native workbook formula.
B26: Change in operating NWC | C26: USD millions | D26: 1355 | E26: =E25-D25 -> -295.57664 | F26: =F25-E25 -> -8.0175744 | G26: =G25-F25 -> 52.034058 | H26: =H25-G25 -> 59.680419 | I26: =I25-H25 -> 13.628513 | J26: Native workbook formula.
B27: Free cash flow to the firm | C27: USD millions | D27: 1733.9169 | E27: =E19+E21-E23-E26 -> 2540.4975 | F27: =F19+F21-F23-F26 -> 2160.8165 | G27: =G19+G21-G23-G26 -> 2359.233 | H27: =H19+H21-H23-H26 -> 2631.951 | I27: =I19+I21-I23-I26 -> 2988.0788 | J27: NOPAT + D&A - capex - change in operating NWC.
B32: Base scenario
B33: Metric | C33: Unit | D33: FY2026A | E33: FY2027E | F33: FY2028E | G33: FY2029E | H33: FY2030E | I33: FY2031E | J33: Source / formula
B34: Revenue growth | C34: decimal | D34: 0.001922 | E34: =Sources!$D$60 -> -0.02 | F34: =Sources!$D$67 -> 0.02 | G34: =Sources!$D$74 -> 0.035 | H34: =Sources!$D$81 -> 0.04 | I34: =Sources!$D$88 -> 0.03 | J34: Approved scenario driver linked from Sources.
B35: Revenue | C35: USD millions | D35: 46398 | E35: =D35*(1+E34) -> 45470.04 | F35: =E35*(1+F34) -> 46379.441 | G35: =F35*(1+G34) -> 48002.721 | H35: =G35*(1+H34) -> 49922.83 | I35: =H35*(1+I34) -> 51420.515 | J35: Native workbook formula.
B36: Gross margin | C36: decimal | D36: 0.429135 | E36: =Sources!$D$61 -> 0.425 | F36: =Sources!$D$68 -> 0.432 | G36: =Sources!$D$75 -> 0.44 | H36: =Sources!$D$82 -> 0.445 | I36: =Sources!$D$89 -> 0.448 | J36: Approved scenario driver linked from Sources.
B37: Gross profit | C37: USD millions | D37: 19911 | E37: =E35*E36 -> 19324.767 | F37: =F35*F36 -> 20035.918 | G37: =G35*G36 -> 21121.197 | H37: =H35*H36 -> 22215.659 | I37: =I35*I36 -> 23036.391 | J37: Native workbook formula.
B38: SG&A / revenue | C38: decimal | D38: 0.34729945 | E38: =Sources!$D$62 -> 0.352 | F38: =Sources!$D$69 -> 0.345 | G38: =Sources!$D$76 -> 0.338 | H38: =Sources!$D$83 -> 0.332 | I38: =Sources!$D$90 -> 0.328 | J38: Approved scenario driver linked from Sources.
B39: Total SG&A | C39: USD millions | D39: 16114 | E39: =E35*E38 -> 16005.454 | F39: =F35*F38 -> 16000.907 | G39: =G35*G38 -> 16224.92 | H39: =H35*H38 -> 16574.38 | I39: =I35*I38 -> 16865.929 | J39: Native workbook formula.
B40: Derived operating income | C40: USD millions | D40: 3797 | E40: =E37-E39 -> 3319.3129 | F40: =F37-F39 -> 4035.0113 | G40: =G37-G39 -> 4896.2776 | H40: =H37-H39 -> 5641.2798 | I40: =I37-I39 -> 6170.4618 | J40: Gross profit less total SG&A; not Nike-reported or segment EBIT.
B41: Derived operating margin | C41: decimal | D41: 0.081835 | E41: =E40/E35 -> 0.073 | F41: =F40/F35 -> 0.087 | G41: =G40/G35 -> 0.102 | H41: =H40/H35 -> 0.113 | I41: =I40/I35 -> 0.12 | J41: Native workbook formula.
B42: Operating tax rate | C42: decimal | D42: 0.20307692 | E42: =Sources!$D$63 -> 0.21 | F42: =Sources!$D$70 -> 0.21 | G42: =Sources!$D$77 -> 0.21 | H42: =Sources!$D$84 -> 0.21 | I42: =Sources!$D$91 -> 0.21 | J42: Approved scenario driver linked from Sources.
B43: Normalized operating tax expense | C43: USD millions | D43: 771.08308 | E43: =MAX(E40,0)*E42 -> 697.05571 | F43: =MAX(F40,0)*F42 -> 847.35238 | G43: =MAX(G40,0)*G42 -> 1028.2183 | H43: =MAX(H40,0)*H42 -> 1184.6688 | I43: =MAX(I40,0)*I42 -> 1295.797 | J43: Native workbook formula.
B44: NOPAT | C44: USD millions | D44: 3025.9169 | E44: =E40-E43 -> 2622.2572 | F44: =F40-F43 -> 3187.659 | G44: =G40-G43 -> 3868.0593 | H44: =H40-H43 -> 4456.611 | I44: =I40-I43 -> 4874.6648 | J44: Native workbook formula.
B45: D&A / revenue | C45: decimal | D45: 0.016099832 | E45: =Sources!$D$64 -> 0.016 | F45: =Sources!$D$71 -> 0.016 | G45: =Sources!$D$78 -> 0.016 | H45: =Sources!$D$85 -> 0.016 | I45: =Sources!$D$92 -> 0.016 | J45: Approved scenario driver linked from Sources.
B46: Depreciation and amortization | C46: USD millions | D46: 747 | E46: =E35*E45 -> 727.52064 | F46: =F35*F45 -> 742.07105 | G46: =G35*G45 -> 768.04354 | H46: =H35*H45 -> 798.76528 | I46: =I35*I45 -> 822.72824 | J46: Native workbook formula.
B47: Capex / revenue | C47: decimal | D47: 0.014742015 | E47: =Sources!$D$65 -> 0.015 | F47: =Sources!$D$72 -> 0.016 | G47: =Sources!$D$79 -> 0.017 | H47: =Sources!$D$86 -> 0.017 | I47: =Sources!$D$93 -> 0.017 | J47: Approved scenario driver linked from Sources.
B48: Capital expenditures | C48: USD millions | D48: 684 | E48: =E35*E47 -> 682.0506 | F48: =F35*F47 -> 742.07105 | G48: =G35*G47 -> 816.04626 | H48: =H35*H47 -> 848.68811 | I48: =I35*I47 -> 874.14875 | J48: Native workbook formula.
B49: Operating NWC / revenue | C49: decimal | D49: 0.11869046 | E49: =Sources!$D$66 -> 0.111 | F49: =Sources!$D$73 -> 0.108 | G49: =Sources!$D$80 -> 0.105 | H49: =Sources!$D$87 -> 0.102 | I49: =Sources!$D$94 -> 0.1 | J49: Approved scenario driver linked from Sources.
B50: Operating NWC proxy | C50: USD millions | D50: 5507 | E50: =E35*E49 -> 5047.1744 | F50: =F35*F49 -> 5008.9796 | G50: =G35*G49 -> 5040.2857 | H50: =H35*H49 -> 5092.1287 | I50: =I35*I49 -> 5142.0515 | J50: Native workbook formula.
B51: Change in operating NWC | C51: USD millions | D51: 1355 | E51: =E50-D50 -> -459.82556 | F51: =F50-E50 -> -38.194834 | G51: =G50-F50 -> 31.306123 | H51: =H50-G50 -> 51.842939 | I51: =I50-H50 -> 49.92283 | J51: Native workbook formula.
B52: Free cash flow to the firm | C52: USD millions | D52: 1733.9169 | E52: =E44+E46-E48-E51 -> 3127.5528 | F52: =F44+F46-F48-F51 -> 3225.8538 | G52: =G44+G46-G48-G51 -> 3788.7504 | H52: =H44+H46-H48-H51 -> 4354.8453 | I52: =I44+I46-I48-I51 -> 4773.3215 | J52: NOPAT + D&A - capex - change in operating NWC.
B57: Bull scenario
B58: Metric | C58: Unit | D58: FY2026A | E58: FY2027E | F58: FY2028E | G58: FY2029E | H58: FY2030E | I58: FY2031E | J58: Source / formula
B59: Revenue growth | C59: decimal | D59: 0.001922 | E59: =Sources!$D$95 -> 0.005 | F59: =Sources!$D$102 -> 0.04 | G59: =Sources!$D$109 -> 0.05 | H59: =Sources!$D$116 -> 0.05 | I59: =Sources!$D$123 -> 0.035 | J59: Approved scenario driver linked from Sources.
B60: Revenue | C60: USD millions | D60: 46398 | E60: =D60*(1+E59) -> 46629.99 | F60: =E60*(1+F59) -> 48495.19 | G60: =F60*(1+G59) -> 50919.949 | H60: =G60*(1+H59) -> 53465.947 | I60: =H60*(1+I59) -> 55337.255 | J60: Native workbook formula.
B61: Gross margin | C61: decimal | D61: 0.429135 | E61: =Sources!$D$96 -> 0.43 | F61: =Sources!$D$103 -> 0.44 | G61: =Sources!$D$110 -> 0.45 | H61: =Sources!$D$117 -> 0.455 | I61: =Sources!$D$124 -> 0.458 | J61: Approved scenario driver linked from Sources.
B62: Gross profit | C62: USD millions | D62: 19911 | E62: =E60*E61 -> 20050.896 | F62: =F60*F61 -> 21337.883 | G62: =G60*G61 -> 22913.977 | H62: =H60*H61 -> 24327.006 | I62: =I60*I61 -> 25344.463 | J62: Native workbook formula.
B63: SG&A / revenue | C63: decimal | D63: 0.34729945 | E63: =Sources!$D$97 -> 0.348 | F63: =Sources!$D$104 -> 0.34 | G63: =Sources!$D$111 -> 0.33 | H63: =Sources!$D$118 -> 0.322 | I63: =Sources!$D$125 -> 0.318 | J63: Approved scenario driver linked from Sources.
B64: Total SG&A | C64: USD millions | D64: 16114 | E64: =E60*E63 -> 16227.237 | F64: =F60*F63 -> 16488.364 | G64: =G60*G63 -> 16803.583 | H64: =H60*H63 -> 17216.035 | I64: =I60*I63 -> 17597.247 | J64: Native workbook formula.
B65: Derived operating income | C65: USD millions | D65: 3797 | E65: =E62-E64 -> 3823.6592 | F65: =F62-F64 -> 4849.519 | G65: =G62-G64 -> 6110.3939 | H65: =H62-H64 -> 7110.9709 | I65: =I62-I64 -> 7747.2157 | J65: Gross profit less total SG&A; not Nike-reported or segment EBIT.
B66: Derived operating margin | C66: decimal | D66: 0.081835 | E66: =E65/E60 -> 0.082 | F66: =F65/F60 -> 0.1 | G66: =G65/G60 -> 0.12 | H66: =H65/H60 -> 0.133 | I66: =I65/I60 -> 0.14 | J66: Native workbook formula.
B67: Operating tax rate | C67: decimal | D67: 0.20307692 | E67: =Sources!$D$98 -> 0.21 | F67: =Sources!$D$105 -> 0.21 | G67: =Sources!$D$112 -> 0.21 | H67: =Sources!$D$119 -> 0.21 | I67: =Sources!$D$126 -> 0.21 | J67: Approved scenario driver linked from Sources.
B68: Normalized operating tax expense | C68: USD millions | D68: 771.08308 | E68: =MAX(E65,0)*E67 -> 802.96843 | F68: =MAX(F65,0)*F67 -> 1018.399 | G68: =MAX(G65,0)*G67 -> 1283.1827 | H68: =MAX(H65,0)*H67 -> 1493.3039 | I68: =MAX(I65,0)*I67 -> 1626.9153 | J68: Native workbook formula.
B69: NOPAT | C69: USD millions | D69: 3025.9169 | E69: =E65-E68 -> 3020.6908 | F69: =F65-F68 -> 3831.12 | G69: =G65-G68 -> 4827.2112 | H69: =H65-H68 -> 5617.667 | I69: =I65-I68 -> 6120.3004 | J69: Native workbook formula.
B70: D&A / revenue | C70: decimal | D70: 0.016099832 | E70: =Sources!$D$99 -> 0.016 | F70: =Sources!$D$106 -> 0.016 | G70: =Sources!$D$113 -> 0.016 | H70: =Sources!$D$120 -> 0.017 | I70: =Sources!$D$127 -> 0.017 | J70: Approved scenario driver linked from Sources.
B71: Depreciation and amortization | C71: USD millions | D71: 747 | E71: =E60*E70 -> 746.07984 | F71: =F60*F70 -> 775.92303 | G71: =G60*G70 -> 814.71919 | H71: =H60*H70 -> 908.92109 | I71: =I60*I70 -> 940.73333 | J71: Native workbook formula.
B72: Capex / revenue | C72: decimal | D72: 0.014742015 | E72: =Sources!$D$100 -> 0.017 | F72: =Sources!$D$107 -> 0.018 | G72: =Sources!$D$114 -> 0.019 | H72: =Sources!$D$121 -> 0.019 | I72: =Sources!$D$128 -> 0.018 | J72: Approved scenario driver linked from Sources.
B73: Capital expenditures | C73: USD millions | D73: 684 | E73: =E60*E72 -> 792.70983 | F73: =F60*F72 -> 872.91341 | G73: =G60*G72 -> 967.47903 | H73: =H60*H72 -> 1015.853 | I73: =I60*I72 -> 996.07058 | J73: Native workbook formula.
B74: Operating NWC / revenue | C74: decimal | D74: 0.11869046 | E74: =Sources!$D$101 -> 0.108 | F74: =Sources!$D$108 -> 0.104 | G74: =Sources!$D$115 -> 0.1 | H74: =Sources!$D$122 -> 0.097 | I74: =Sources!$D$129 -> 0.095 | J74: Approved scenario driver linked from Sources.
B75: Operating NWC proxy | C75: USD millions | D75: 5507 | E75: =E60*E74 -> 5036.0389 | F75: =F60*F74 -> 5043.4997 | G75: =G60*G74 -> 5091.9949 | H75: =H60*H74 -> 5186.1968 | I75: =I60*I74 -> 5257.0392 | J75: Native workbook formula.
B76: Change in operating NWC | C76: USD millions | D76: 1355 | E76: =E75-D75 -> -470.96108 | F76: =F75-E75 -> 7.4607984 | G76: =G75-F75 -> 48.49519 | H76: =H75-G75 -> 94.201906 | I76: =I75-H75 -> 70.842379 | J76: Native workbook formula.
B77: Free cash flow to the firm | C77: USD millions | D77: 1733.9169 | E77: =E69+E71-E73-E76 -> 3445.0218 | F77: =F69+F71-F73-F76 -> 3726.6688 | G77: =G69+G71-G73-G76 -> 4625.9561 | H77: =H69+H71-H73-H76 -> 5416.5332 | I77: =I69+I71-I73-I76 -> 5994.1207 | J77: NOPAT + D&A - capex - change in operating NWC.

Sheet WACC
B2: Weighted average cost of capital
B3: Primary build uses fair-value debt; carrying-debt build is a cross-check
B7: Primary fair-value-debt WACC | G7: Carrying-debt WACC cross-check
B8: Metric | C8: Unit | D8: Source / formula | E8: Value | G8: Metric | H8: Unit | I8: Source / formula | J8: Value
B9: Reference market price | C9: USD per share | D9: ReferenceMarketPrice | E9: =ReferenceMarketPrice -> 38.4 | G9: Reference market price | H9: USD per share | I9: ReferenceMarketPrice | J9: =ReferenceMarketPrice -> 38.4
B10: Class A shares | C10: millions | D10: ClassAShares | E10: =ClassAShares -> 281.38775 | G10: Class A shares | H10: millions | I10: ClassAShares | J10: =ClassAShares -> 281.38775
B11: Class B shares | C11: millions | D11: ClassBShares | E11: =ClassBShares -> 1202.111 | G11: Class B shares | H11: millions | I11: ClassBShares | J11: =ClassBShares -> 1202.111
B12: Basic shares | C12: millions | D12: E10+E11 | E12: =E10+E11 -> 1483.4987 | G12: Basic shares | H12: millions | I12: J10+J11 | J12: =J10+J11 -> 1483.4987
B13: Market equity | C13: USD millions | D13: E9*E12 | E13: =E9*E12 -> 56966.35 | G13: Market equity | H13: USD millions | I13: J9*J12 | J13: =J9*J12 -> 56966.35
B14: Footwear revenue | C14: USD millions | D14: 'Sources'!D23 | E14: =Sources!D23 -> 30538 | G14: Footwear revenue | H14: USD millions | I14: 'Sources'!D23 | J14: =Sources!D23 -> 30538
B15: Footwear unlevered beta | C15: x | D15: 'Sources'!D27 | E15: =Sources!D27 -> 1 | G15: Footwear unlevered beta | H15: x | I15: 'Sources'!D27 | J15: =Sources!D27 -> 1
B16: Apparel revenue | C16: USD millions | D16: 'Sources'!D24 | E16: =Sources!D24 -> 13497 | G16: Apparel revenue | H16: USD millions | I16: 'Sources'!D24 | J16: =Sources!D24 -> 13497
B17: Apparel unlevered beta | C17: x | D17: 'Sources'!D28 | E17: =Sources!D28 -> 0.79 | G17: Apparel unlevered beta | H17: x | I17: 'Sources'!D28 | J17: =Sources!D28 -> 0.79
B18: Equipment revenue | C18: USD millions | D18: 'Sources'!D25 | E18: =Sources!D25 -> 2220 | G18: Equipment revenue | H18: USD millions | I18: 'Sources'!D25 | J18: =Sources!D25 -> 2220
B19: Equipment unlevered beta | C19: x | D19: 'Sources'!D29 | E19: =Sources!D29 -> 0.74 | G19: Equipment unlevered beta | H19: x | I19: 'Sources'!D29 | J19: =Sources!D29 -> 0.74
B20: Classified product revenue | C20: USD millions | D20: E14+E16+E18 | E20: =E14+E16+E18 -> 46255 | G20: Classified product revenue | H20: USD millions | I20: J14+J16+J18 | J20: =J14+J16+J18 -> 46255
B21: Other revenue | C21: USD millions | D21: 'Sources'!D26 | E21: =Sources!D26 -> 143 | G21: Other revenue | H21: USD millions | I21: 'Sources'!D26 | J21: =Sources!D26 -> 143
B22: Total revenue | C22: USD millions | D22: E20+E21 | E22: =E20+E21 -> 46398 | G22: Total revenue | H22: USD millions | I22: J20+J21 | J22: =J20+J21 -> 46398
B23: Product-weighted unlevered beta | C23: x | D23: (E14*E15+E16*E17+E18*E19)/E20 | E23: =(E14*E15+E16*E17+E18*E19)/E20 -> 0.9262443 | G23: Product-weighted unlevered beta | H23: x | I23: (J14*J15+J16*J17+J18*J19)/J20 | J23: =(J14*J15+J16*J17+J18*J19)/J20 -> 0.9262443
B24: Debt used | C24: USD millions | D24: FairValueDebt | E24: =FairValueDebt -> 6800 | G24: Debt used | H24: USD millions | I24: CarryingDebt | J24: =CarryingDebt -> 7942
B25: Debt / equity | C25: decimal | D25: E24/E13 | E25: =E24/E13 -> 0.11936871 | G25: Debt / equity | H25: decimal | I25: J24/J13 | J25: =J24/J13 -> 0.13941564
B26: Operating tax rate | C26: decimal | D26: OperatingTaxRate | E26: =OperatingTaxRate -> 0.21 | G26: Operating tax rate | H26: decimal | I26: OperatingTaxRate | J26: =OperatingTaxRate -> 0.21
B27: Relevered beta | C27: x | D27: E23*(1+(1-E26)*E24/E13) | E27: =E23*(1+(1-E26)*E24/E13) -> 1.0135903 | G27: Relevered beta | H27: x | I27: J23*(1+(1-J26)*J24/J13) | J27: =J23*(1+(1-J26)*J24/J13) -> 1.0282593
B28: Risk-free rate | C28: decimal | D28: RiskFreeRate | E28: =RiskFreeRate -> 0.0478 | G28: Risk-free rate | H28: decimal | I28: RiskFreeRate | J28: =RiskFreeRate -> 0.0478
B29: Equity-risk premium | C29: decimal | D29: EquityRiskPremium | E29: =EquityRiskPremium -> 0.0414 | G29: Equity-risk premium | H29: decimal | I29: EquityRiskPremium | J29: =EquityRiskPremium -> 0.0414
B30: Cost of equity | C30: decimal | D30: E28+E27*E29 | E30: =E28+E27*E29 -> 0.089762639 | G30: Cost of equity | H30: decimal | I30: J28+J27*J29 | J30: =J28+J27*J29 -> 0.090369936
B31: Debt default spread | C31: decimal | D31: DebtDefaultSpread | E31: =DebtDefaultSpread -> 0.0078 | G31: Debt default spread | H31: decimal | I31: DebtDefaultSpread | J31: =DebtDefaultSpread -> 0.0078
B32: Pretax cost of debt | C32: decimal | D32: E28+E31 | E32: =E28+E31 -> 0.0556 | G32: Pretax cost of debt | H32: decimal | I32: J28+J31 | J32: =J28+J31 -> 0.0556
B33: After-tax cost of debt | C33: decimal | D33: E32*(1-E26) | E33: =E32*(1-E26) -> 0.043924 | G33: After-tax cost of debt | H33: decimal | I33: J32*(1-J26) | J33: =J32*(1-J26) -> 0.043924
B34: Equity weight | C34: decimal | D34: E13/(E13+E24) | E34: =E13/(E13+E24) -> 0.89336068 | G34: Equity weight | H34: decimal | I34: J13/(J13+J24) | J34: =J13/(J13+J24) -> 0.87764286
B35: Debt weight | C35: decimal | D35: E24/(E13+E24) | E35: =E24/(E13+E24) -> 0.10663932 | G35: Debt weight | H35: decimal | I35: J24/(J13+J24) | J35: =J24/(J13+J24) -> 0.12235714
B36: Calculated WACC | C36: decimal | D36: E34*E30+E35*E33 | E36: =E34*E30+E35*E33 -> 0.084874438 | G36: Calculated WACC | H36: decimal | I36: J34*J30+J35*J33 | J36: =J34*J30+J35*J33 -> 0.084686944

Sheet DCF
B2: Discounted cash flow
B3: Full-year FY2027-FY2031 FCFF discounted from Sep. 4, 2026; May 31, 2026 equity-bridge balances are not rolled forward
B6: Selected scenario | D6: =SelectedScenario -> Base
K7: All-scenario valuation outputs
K8: Metric | L8: Bear | M8: Base | N8: Bull
B9: Explicit forecast | K9: PV of explicit FCFF | L9: =SUMPRODUCT(Scenarios!E27:I27,1/(1+CalculatedWACC)^(($E$12:$I$12-ModelDate)/365)) -> 10126.755 | M9: =SUMPRODUCT(Scenarios!E52:I52,1/(1+CalculatedWACC)^(($E$12:$I$12-ModelDate)/365)) -> 15231.303 | N9: =SUMPRODUCT(Scenarios!E77:I77,1/(1+CalculatedWACC)^(($E$12:$I$12-ModelDate)/365)) -> 18247.274
B10: Metric | C10: Unit | D10: Model date | E10: FY2027E | F10: FY2028E | G10: FY2029E | H10: FY2030E | I10: FY2031E | K10: FY2032 revenue | L10: =Scenarios!I10*(1+TerminalGrowth) -> 47495.37 | M10: =Scenarios!I35*(1+TerminalGrowth) -> 52706.028 | N10: =Scenarios!I60*(1+TerminalGrowth) -> 56720.686
K11: FY2032 gross profit | L11: =L10*Scenarios!I11 -> 20328.018 | M11: =M10*Scenarios!I36 -> 23612.3 | N11: =N10*Scenarios!I61 -> 25978.074
B12: Cash-flow date | C12: date | D12: 46269 | E12: 46538 | F12: 46904 | G12: 47269 | H12: 47634 | I12: 47999 | K12: FY2032 total SG&A | L12: =L10*Scenarios!I13 -> 16433.398 | M12: =M10*Scenarios!I38 -> 17287.577 | N12: =N10*Scenarios!I63 -> 18037.178
B13: FCFF | C13: USD millions | D13: 0 | E13: =CHOOSE(MATCH(SelectedScenario,ScenarioList,0),Scenarios!E27,Scenarios!E52,Scenarios!E77) -> 3127.5528 | F13: =CHOOSE(MATCH(SelectedScenario,ScenarioList,0),Scenarios!F27,Scenarios!F52,Scenarios!F77) -> 3225.8538 | G13: =CHOOSE(MATCH(SelectedScenario,ScenarioList,0),Scenarios!G27,Scenarios!G52,Scenarios!G77) -> 3788.7504 | H13: =CHOOSE(MATCH(SelectedScenario,ScenarioList,0),Scenarios!H27,Scenarios!H52,Scenarios!H77) -> 4354.8453 | I13: =CHOOSE(MATCH(SelectedScenario,ScenarioList,0),Scenarios!I27,Scenarios!I52,Scenarios!I77) -> 4773.3215 | K13: FY2032 derived operating income | L13: =L11-L12 -> 3894.6203 | M13: =M11-M12 -> 6324.7233 | N13: =N11-N12 -> 7940.896
B14: Discount exponent | C14: x | D14: =(D12-ModelDate)/365 -> 0 | E14: =(E12-ModelDate)/365 -> 0.7369863 | F14: =(F12-ModelDate)/365 -> 1.739726 | G14: =(G12-ModelDate)/365 -> 2.739726 | H14: =(H12-ModelDate)/365 -> 3.739726 | I14: =(I12-ModelDate)/365 -> 4.739726 | K14: FY2032 operating tax expense | L14: =MAX(L13,0)*Scenarios!I17 -> 817.87026 | M14: =MAX(M13,0)*Scenarios!I42 -> 1328.1919 | N14: =MAX(N13,0)*Scenarios!I67 -> 1667.5882
B15: Discount factor | C15: x | D15: =1/(1+CalculatedWACC)^D14 -> 1 | E15: =1/(1+CalculatedWACC)^E14 -> 0.94172871 | F15: =1/(1+CalculatedWACC)^F14 -> 0.86785946 | G15: =1/(1+CalculatedWACC)^G14 -> 0.79996305 | H15: =1/(1+CalculatedWACC)^H14 -> 0.73737847 | I15: =1/(1+CalculatedWACC)^I14 -> 0.67969015 | K15: FY2032 NOPAT | L15: =L13-L14 -> 3076.75 | M15: =M13-M14 -> 4996.5314 | N15: =N13-N14 -> 6273.3079
B16: Present value of FCFF | C16: USD millions | D16: =D13*D15 -> 0 | E16: =E13*E15 -> 2945.3063 | F16: =F13*F15 -> 2799.5878 | G16: =G13*G15 -> 3030.8604 | H16: =H13*H15 -> 3211.1691 | I16: =I13*I15 -> 3244.3796 | K16: FY2032 D&A | L16: =L10*Scenarios!I20 -> 712.43054 | M16: =M10*Scenarios!I45 -> 843.29645 | N16: =N10*Scenarios!I70 -> 964.25166
K17: FY2032 capex | L17: =L10*Scenarios!I22 -> 712.43054 | M17: =M10*Scenarios!I47 -> 896.00247 | N17: =N10*Scenarios!I72 -> 1020.9723
B18: Total explicit-period PV | I18: =SUM(E16:I16) -> 15231.303 | K18: FY2032 operating NWC | L18: =L10*Scenarios!I24 -> 5461.9675 | M18: =M10*Scenarios!I49 -> 5270.6028 | N18: =N10*Scenarios!I74 -> 5388.4652
K19: FY2032 change in operating NWC | L19: =L18-Scenarios!I25 -> 133.21872 | M19: =M18-Scenarios!I50 -> 128.55129 | N19: =N18-Scenarios!I75 -> 131.42598
K20: FY2032 FCFF | L20: =L15+L16-L17-L19 -> 2943.5313 | M20: =M15+M16-M17-M19 -> 4815.2741 | N20: =N15+N16-N17-N19 -> 6085.1612
B21: FY2032 terminal transition | K21: FY2032 EBITDA proxy | L21: =L13+L16 -> 4607.0508 | M21: =M13+M16 -> 7168.0198 | N21: =N13+N16 -> 8905.1477
B22: Metric | C22: Unit | D22: FY2031E | E22: FY2032 terminal | K22: Terminal value | L22: =L20/(CalculatedWACC-TerminalGrowth) -> 49161.736 | M22: =M20/(CalculatedWACC-TerminalGrowth) -> 80422.869 | N22: =N20/(CalculatedWACC-TerminalGrowth) -> 101632.04
B23: Revenue growth | C23: decimal | D23: =CHOOSE(MATCH(SelectedScenario,ScenarioList,0),Scenarios!I9,Scenarios!I34,Scenarios!I59) -> 0.03 | E23: =TerminalGrowth -> 0.025 | K23: PV of terminal value | L23: =L22/(1+CalculatedWACC)^((DATE(2031,5,31)-ModelDate)/365) -> 33414.747 | M23: =M22/(1+CalculatedWACC)^((DATE(2031,5,31)-ModelDate)/365) -> 54662.632 | N23: =N22/(1+CalculatedWACC)^((DATE(2031,5,31)-ModelDate)/365) -> 69078.295
B24: Revenue | C24: USD millions | D24: =CHOOSE(MATCH(SelectedScenario,ScenarioList,0),Scenarios!I10,Scenarios!I35,Scenarios!I60) -> 51420.515 | E24: =D24*(1+E23) -> 52706.028 | K24: Enterprise value | L24: =L9+L23 -> 43541.503 | M24: =M9+M23 -> 69893.935 | N24: =N9+N23 -> 87325.57
B25: Gross margin | C25: decimal | D25: =CHOOSE(MATCH(SelectedScenario,ScenarioList,0),Scenarios!I11,Scenarios!I36,Scenarios!I61) -> 0.448 | E25: =D25 -> 0.448 | K25: Equity value | L25: =L24+CashAndShortTermInvestments-CarryingDebt-RedeemablePreferredStock -> 44626.203 | M25: =M24+CashAndShortTermInvestments-CarryingDebt-RedeemablePreferredStock -> 70978.635 | N25: =N24+CashAndShortTermInvestments-CarryingDebt-RedeemablePreferredStock -> 88410.27
B26: Gross profit | C26: USD millions | D26: =CHOOSE(MATCH(SelectedScenario,ScenarioList,0),Scenarios!I12,Scenarios!I37,Scenarios!I62) -> 23036.391 | E26: =E24*E25 -> 23612.3 | K26: Illustrative value per share | L26: =L25/DilutedProxyShares -> 30.057414 | M26: =M25/DilutedProxyShares -> 47.80676 | N26: =N25/DilutedProxyShares -> 59.547617
B27: SG&A / revenue | C27: decimal | D27: =CHOOSE(MATCH(SelectedScenario,ScenarioList,0),Scenarios!I13,Scenarios!I38,Scenarios!I63) -> 0.328 | E27: =D27 -> 0.328 | K27: Basic-share cross-check | L27: =L25/BasicShares -> 30.081727 | M27: =M25/BasicShares -> 47.845431 | N27: =N25/BasicShares -> 59.595785
B28: Total SG&A | C28: USD millions | D28: =CHOOSE(MATCH(SelectedScenario,ScenarioList,0),Scenarios!I14,Scenarios!I39,Scenarios!I64) -> 16865.929 | E28: =E24*E27 -> 17287.577 | K28: Premium / (discount) | L28: =L26/ReferenceMarketPrice-1 -> -0.21725486 | M28: =M26/ReferenceMarketPrice-1 -> 0.24496772 | N28: =N26/ReferenceMarketPrice-1 -> 0.55071919
B29: Derived operating income | C29: USD millions | D29: =CHOOSE(MATCH(SelectedScenario,ScenarioList,0),Scenarios!I15,Scenarios!I40,Scenarios!I65) -> 6170.4618 | E29: =E26-E28 -> 6324.7233 | K29: PV terminal / EV | L29: =L23/L24 -> 0.76742292 | M29: =M23/M24 -> 0.78207976 | N29: =N23/N24 -> 0.79104317
B30: Derived operating margin | C30: decimal | D30: =CHOOSE(MATCH(SelectedScenario,ScenarioList,0),Scenarios!I16,Scenarios!I41,Scenarios!I66) -> 0.12 | E30: =E29/E24 -> 0.12 | K30: Terminal EV / EBITDA | L30: =L22/L21 -> 10.670977 | M30: =M22/M21 -> 11.219677 | N30: =N22/N21 -> 11.412729
B31: Operating tax rate | C31: decimal | D31: =CHOOSE(MATCH(SelectedScenario,ScenarioList,0),Scenarios!I17,Scenarios!I42,Scenarios!I67) -> 0.21 | E31: =D31 -> 0.21
B32: Normalized operating tax expense | C32: USD millions | D32: =CHOOSE(MATCH(SelectedScenario,ScenarioList,0),Scenarios!I18,Scenarios!I43,Scenarios!I68) -> 1295.797 | E32: =MAX(E29,0)*E31 -> 1328.1919
B33: NOPAT | C33: USD millions | D33: =CHOOSE(MATCH(SelectedScenario,ScenarioList,0),Scenarios!I19,Scenarios!I44,Scenarios!I69) -> 4874.6648 | E33: =E29-E32 -> 4996.5314
B34: D&A / revenue | C34: decimal | D34: =CHOOSE(MATCH(SelectedScenario,ScenarioList,0),Scenarios!I20,Scenarios!I45,Scenarios!I70) -> 0.016 | E34: =D34 -> 0.016
B35: Depreciation and amortization | C35: USD millions | D35: =CHOOSE(MATCH(SelectedScenario,ScenarioList,0),Scenarios!I21,Scenarios!I46,Scenarios!I71) -> 822.72824 | E35: =E24*E34 -> 843.29645
B36: Capex / revenue | C36: decimal | D36: =CHOOSE(MATCH(SelectedScenario,ScenarioList,0),Scenarios!I22,Scenarios!I47,Scenarios!I72) -> 0.017 | E36: =D36 -> 0.017
B37: Capital expenditures | C37: USD millions | D37: =CHOOSE(MATCH(SelectedScenario,ScenarioList,0),Scenarios!I23,Scenarios!I48,Scenarios!I73) -> 874.14875 | E37: =E24*E36 -> 896.00247
B38: Operating NWC / revenue | C38: decimal | D38: =CHOOSE(MATCH(SelectedScenario,ScenarioList,0),Scenarios!I24,Scenarios!I49,Scenarios!I74) -> 0.1 | E38: =D38 -> 0.1
B39: Operating NWC proxy | C39: USD millions | D39: =CHOOSE(MATCH(SelectedScenario,ScenarioList,0),Scenarios!I25,Scenarios!I50,Scenarios!I75) -> 5142.0515 | E39: =E24*E38 -> 5270.6028
B40: Change in operating NWC | C40: USD millions | D40: =CHOOSE(MATCH(SelectedScenario,ScenarioList,0),Scenarios!I26,Scenarios!I51,Scenarios!I76) -> 49.92283 | E40: =E39-D39 -> 128.55129
B41: Terminal-year FCFF | C41: USD millions | D41: =CHOOSE(MATCH(SelectedScenario,ScenarioList,0),Scenarios!I27,Scenarios!I52,Scenarios!I77) -> 4773.3215 | E41: =E33+E35-E37-E40 -> 4815.2741
B42: Terminal EBITDA proxy | C42: USD millions | D42: =D29+D35 -> 6993.19 | E42: =E29+E35 -> 7168.0198
B45: Terminal value | E45: =E41/(CalculatedWACC-TerminalGrowth) -> 80422.869
B46: Present value of terminal value | E46: =E45/(1+CalculatedWACC)^((DATE(2031,5,31)-ModelDate)/365) -> 54662.632
B49: Enterprise-to-equity bridge
B50: PV of explicit FCFF | E50: =I18 -> 15231.303
B51: PV of terminal value | E51: =E46 -> 54662.632
B52: Enterprise value | E52: =E50+E51 -> 69893.935
B53: Cash and short-term investments | E53: =CashAndShortTermInvestments -> 9027
B54: Less: carrying interest-bearing debt | E54: =CarryingDebt -> 7942
B55: Less: redeemable preferred stock | E55: =RedeemablePreferredStock -> 0.3
B56: Other adjustments | E56: =0 -> 0
B57: Equity value | E57: =E52+E53-E54-E55+E56 -> 70978.635
B58: Diluted-proxy shares | E58: =DilutedProxyShares -> 1484.6987
B59: Illustrative value per share | E59: =E57/E58 -> 47.80676
B60: Basic-share denominator cross-check | E60: =E57/BasicShares -> 47.845431
B61: September 4, 2026 reference price | E61: =ReferenceMarketPrice -> 38.4
B62: Premium / (discount) to reference | E62: =E59/E61-1 -> 0.24496772
B63: PV of terminal value / enterprise value | E63: =E51/E52 -> 0.78207976
B64: Implied terminal EV / EBITDA | E64: =E45/E42 -> 11.219677
B65: Operating lease liabilities (memorandum) | E65: =OperatingLeaseLiabilitiesMemo -> 3091
B67: Native XNPV enterprise value | E67: =XNPV(CalculatedWACC,D71:I71,D12:I12) -> 69893.935
B68: Explicit date-exponent enterprise value | E68: =E52 -> 69893.935
B69: XNPV reconciliation difference | E69: =E67-E68 -> 0
B71: XNPV cash-flow helper | D71: 0 | E71: =E13 -> 3127.5528 | F71: =F13 -> 3225.8538 | G71: =G13 -> 3788.7504 | H71: =H13 -> 4354.8453 | I71: =I13+E45 -> 85196.191

Sheet Sensitivity
B2: Base-case sensitivity
B3: Illustrative value per diluted-proxy share; full-precision WACC and perpetual-growth inputs
B7: WACC / perpetual growth
C8: WACC | D8: =Sources!$D$36 -> 0.015 | E8: =Sources!$D$37 -> 0.02 | F8: =Sources!$D$38 -> 0.025 | G8: =Sources!$D$39 -> 0.03 | H8: =Sources!$D$40 -> 0.035
C9: =CalculatedWACC+Sources!$D$31 -> 0.074874438 | D9: =(SUMPRODUCT(Scenarios!E52:I52,1/(1+$C9)^((DCF!$E$12:$I$12-ModelDate)/365))+(D29/($C9-D$8))/(1+$C9)^((DATE(2031,5,31)-ModelDate)/365)+CashAndShortTermInvestments-CarryingDebt-RedeemablePreferredStock)/DilutedProxyShares -> 49.755123 | E9: =(SUMPRODUCT(Scenarios!E52:I52,1/(1+$C9)^((DCF!$E$12:$I$12-ModelDate)/365))+(E29/($C9-E$8))/(1+$C9)^((DATE(2031,5,31)-ModelDate)/365)+CashAndShortTermInvestments-CarryingDebt-RedeemablePreferredStock)/DilutedProxyShares -> 53.248759 | F9: =(SUMPRODUCT(Scenarios!E52:I52,1/(1+$C9)^((DCF!$E$12:$I$12-ModelDate)/365))+(F29/($C9-F$8))/(1+$C9)^((DATE(2031,5,31)-ModelDate)/365)+CashAndShortTermInvestments-CarryingDebt-RedeemablePreferredStock)/DilutedProxyShares -> 57.442881 | G9: =(SUMPRODUCT(Scenarios!E52:I52,1/(1+$C9)^((DCF!$E$12:$I$12-ModelDate)/365))+(G29/($C9-G$8))/(1+$C9)^((DATE(2031,5,31)-ModelDate)/365)+CashAndShortTermInvestments-CarryingDebt-RedeemablePreferredStock)/DilutedProxyShares -> 62.571639 | H9: =(SUMPRODUCT(Scenarios!E52:I52,1/(1+$C9)^((DCF!$E$12:$I$12-ModelDate)/365))+(H29/($C9-H$8))/(1+$C9)^((DATE(2031,5,31)-ModelDate)/365)+CashAndShortTermInvestments-CarryingDebt-RedeemablePreferredStock)/DilutedProxyShares -> 68.986623
C10: =CalculatedWACC+Sources!$D$32 -> 0.079874438 | D10: =(SUMPRODUCT(Scenarios!E52:I52,1/(1+$C10)^((DCF!$E$12:$I$12-ModelDate)/365))+(D29/($C10-D$8))/(1+$C10)^((DATE(2031,5,31)-ModelDate)/365)+CashAndShortTermInvestments-CarryingDebt-RedeemablePreferredStock)/DilutedProxyShares -> 45.878409 | E10: =(SUMPRODUCT(Scenarios!E52:I52,1/(1+$C10)^((DCF!$E$12:$I$12-ModelDate)/365))+(E29/($C10-E$8))/(1+$C10)^((DATE(2031,5,31)-ModelDate)/365)+CashAndShortTermInvestments-CarryingDebt-RedeemablePreferredStock)/DilutedProxyShares -> 48.768269 | F10: =(SUMPRODUCT(Scenarios!E52:I52,1/(1+$C10)^((DCF!$E$12:$I$12-ModelDate)/365))+(F29/($C10-F$8))/(1+$C10)^((DATE(2031,5,31)-ModelDate)/365)+CashAndShortTermInvestments-CarryingDebt-RedeemablePreferredStock)/DilutedProxyShares -> 52.18476 | G10: =(SUMPRODUCT(Scenarios!E52:I52,1/(1+$C10)^((DCF!$E$12:$I$12-ModelDate)/365))+(G29/($C10-G$8))/(1+$C10)^((DATE(2031,5,31)-ModelDate)/365)+CashAndShortTermInvestments-CarryingDebt-RedeemablePreferredStock)/DilutedProxyShares -> 56.28627 | H10: =(SUMPRODUCT(Scenarios!E52:I52,1/(1+$C10)^((DCF!$E$12:$I$12-ModelDate)/365))+(H29/($C10-H$8))/(1+$C10)^((DATE(2031,5,31)-ModelDate)/365)+CashAndShortTermInvestments-CarryingDebt-RedeemablePreferredStock)/DilutedProxyShares -> 61.301777
C11: =CalculatedWACC+Sources!$D$33 -> 0.084874438 | D11: =(SUMPRODUCT(Scenarios!E52:I52,1/(1+$C11)^((DCF!$E$12:$I$12-ModelDate)/365))+(D29/($C11-D$8))/(1+$C11)^((DATE(2031,5,31)-ModelDate)/365)+CashAndShortTermInvestments-CarryingDebt-RedeemablePreferredStock)/DilutedProxyShares -> 42.558579 | E11: =(SUMPRODUCT(Scenarios!E52:I52,1/(1+$C11)^((DCF!$E$12:$I$12-ModelDate)/365))+(E29/($C11-E$8))/(1+$C11)^((DATE(2031,5,31)-ModelDate)/365)+CashAndShortTermInvestments-CarryingDebt-RedeemablePreferredStock)/DilutedProxyShares -> 44.980426 | F11: =(SUMPRODUCT(Scenarios!E52:I52,1/(1+$C11)^((DCF!$E$12:$I$12-ModelDate)/365))+(F29/($C11-F$8))/(1+$C11)^((DATE(2031,5,31)-ModelDate)/365)+CashAndShortTermInvestments-CarryingDebt-RedeemablePreferredStock)/DilutedProxyShares -> 47.80676 | G11: =(SUMPRODUCT(Scenarios!E52:I52,1/(1+$C11)^((DCF!$E$12:$I$12-ModelDate)/365))+(G29/($C11-G$8))/(1+$C11)^((DATE(2031,5,31)-ModelDate)/365)+CashAndShortTermInvestments-CarryingDebt-RedeemablePreferredStock)/DilutedProxyShares -> 51.14815 | H11: =(SUMPRODUCT(Scenarios!E52:I52,1/(1+$C11)^((DCF!$E$12:$I$12-ModelDate)/365))+(H29/($C11-H$8))/(1+$C11)^((DATE(2031,5,31)-ModelDate)/365)+CashAndShortTermInvestments-CarryingDebt-RedeemablePreferredStock)/DilutedProxyShares -> 55.1595
C12: =CalculatedWACC+Sources!$D$34 -> 0.089874438 | D12: =(SUMPRODUCT(Scenarios!E52:I52,1/(1+$C12)^((DCF!$E$12:$I$12-ModelDate)/365))+(D29/($C12-D$8))/(1+$C12)^((DATE(2031,5,31)-ModelDate)/365)+CashAndShortTermInvestments-CarryingDebt-RedeemablePreferredStock)/DilutedProxyShares -> 39.684025 | E12: =(SUMPRODUCT(Scenarios!E52:I52,1/(1+$C12)^((DCF!$E$12:$I$12-ModelDate)/365))+(E29/($C12-E$8))/(1+$C12)^((DATE(2031,5,31)-ModelDate)/365)+CashAndShortTermInvestments-CarryingDebt-RedeemablePreferredStock)/DilutedProxyShares -> 41.736497 | F12: =(SUMPRODUCT(Scenarios!E52:I52,1/(1+$C12)^((DCF!$E$12:$I$12-ModelDate)/365))+(F29/($C12-F$8))/(1+$C12)^((DATE(2031,5,31)-ModelDate)/365)+CashAndShortTermInvestments-CarryingDebt-RedeemablePreferredStock)/DilutedProxyShares -> 44.105345 | G12: =(SUMPRODUCT(Scenarios!E52:I52,1/(1+$C12)^((DCF!$E$12:$I$12-ModelDate)/365))+(G29/($C12-G$8))/(1+$C12)^((DATE(2031,5,31)-ModelDate)/365)+CashAndShortTermInvestments-CarryingDebt-RedeemablePreferredStock)/DilutedProxyShares -> 46.869828 | H12: =(SUMPRODUCT(Scenarios!E52:I52,1/(1+$C12)^((DCF!$E$12:$I$12-ModelDate)/365))+(H29/($C12-H$8))/(1+$C12)^((DATE(2031,5,31)-ModelDate)/365)+CashAndShortTermInvestments-CarryingDebt-RedeemablePreferredStock)/DilutedProxyShares -> 50.138095
C13: =CalculatedWACC+Sources!$D$35 -> 0.094874438 | D13: =(SUMPRODUCT(Scenarios!E52:I52,1/(1+$C13)^((DCF!$E$12:$I$12-ModelDate)/365))+(D29/($C13-D$8))/(1+$C13)^((DATE(2031,5,31)-ModelDate)/365)+CashAndShortTermInvestments-CarryingDebt-RedeemablePreferredStock)/DilutedProxyShares -> 37.171087 | E13: =(SUMPRODUCT(Scenarios!E52:I52,1/(1+$C13)^((DCF!$E$12:$I$12-ModelDate)/365))+(E29/($C13-E$8))/(1+$C13)^((DATE(2031,5,31)-ModelDate)/365)+CashAndShortTermInvestments-CarryingDebt-RedeemablePreferredStock)/DilutedProxyShares -> 38.927478 | F13: =(SUMPRODUCT(Scenarios!E52:I52,1/(1+$C13)^((DCF!$E$12:$I$12-ModelDate)/365))+(F29/($C13-F$8))/(1+$C13)^((DATE(2031,5,31)-ModelDate)/365)+CashAndShortTermInvestments-CarryingDebt-RedeemablePreferredStock)/DilutedProxyShares -> 40.935234 | G13: =(SUMPRODUCT(Scenarios!E52:I52,1/(1+$C13)^((DCF!$E$12:$I$12-ModelDate)/365))+(G29/($C13-G$8))/(1+$C13)^((DATE(2031,5,31)-ModelDate)/365)+CashAndShortTermInvestments-CarryingDebt-RedeemablePreferredStock)/DilutedProxyShares -> 43.252474 | H13: =(SUMPRODUCT(Scenarios!E52:I52,1/(1+$C13)^((DCF!$E$12:$I$12-ModelDate)/365))+(H29/($C13-H$8))/(1+$C13)^((DATE(2031,5,31)-ModelDate)/365)+CashAndShortTermInvestments-CarryingDebt-RedeemablePreferredStock)/DilutedProxyShares -> 45.956729
B17: Visible terminal-growth helpers
B18: Perpetual growth | D18: =D$8 -> 0.015 | E18: =E$8 -> 0.02 | F18: =F$8 -> 0.025 | G18: =G$8 -> 0.03 | H18: =H$8 -> 0.035
B19: FY2032 revenue | D19: =Scenarios!I35*(1+D18) -> 52191.823 | E19: =Scenarios!I35*(1+E18) -> 52448.925 | F19: =Scenarios!I35*(1+F18) -> 52706.028 | G19: =Scenarios!I35*(1+G18) -> 52963.13 | H19: =Scenarios!I35*(1+H18) -> 53220.233
B20: FY2032 gross profit | D20: =D19*Scenarios!I36 -> 23381.937 | E20: =E19*Scenarios!I36 -> 23497.119 | F20: =F19*Scenarios!I36 -> 23612.3 | G20: =G19*Scenarios!I36 -> 23727.482 | H20: =H19*Scenarios!I36 -> 23842.664
B21: FY2032 total SG&A | D21: =D19*Scenarios!I38 -> 17118.918 | E21: =E19*Scenarios!I38 -> 17203.247 | F21: =F19*Scenarios!I38 -> 17287.577 | G21: =G19*Scenarios!I38 -> 17371.907 | H21: =H19*Scenarios!I38 -> 17456.236
B22: FY2032 derived operating income | D22: =D20-D21 -> 6263.0187 | E22: =E20-E21 -> 6293.871 | F22: =F20-F21 -> 6324.7233 | G22: =G20-G21 -> 6355.5757 | H22: =H20-H21 -> 6386.428
B23: FY2032 tax expense | D23: =MAX(D22,0)*Scenarios!I42 -> 1315.2339 | E23: =MAX(E22,0)*Scenarios!I42 -> 1321.7129 | F23: =MAX(F22,0)*Scenarios!I42 -> 1328.1919 | G23: =MAX(G22,0)*Scenarios!I42 -> 1334.6709 | H23: =MAX(H22,0)*Scenarios!I42 -> 1341.1499
B24: FY2032 NOPAT | D24: =D22-D23 -> 4947.7848 | E24: =E22-E23 -> 4972.1581 | F24: =F22-F23 -> 4996.5314 | G24: =G22-G23 -> 5020.9048 | H24: =H22-H23 -> 5045.2781
B25: FY2032 D&A | D25: =D19*Scenarios!I45 -> 835.06916 | E25: =E19*Scenarios!I45 -> 839.1828 | F25: =F19*Scenarios!I45 -> 843.29645 | G25: =G19*Scenarios!I45 -> 847.41009 | H25: =H19*Scenarios!I45 -> 851.52373
B26: FY2032 capex | D26: =D19*Scenarios!I47 -> 887.26099 | E26: =E19*Scenarios!I47 -> 891.63173 | F26: =F19*Scenarios!I47 -> 896.00247 | G26: =G19*Scenarios!I47 -> 900.37322 | H26: =H19*Scenarios!I47 -> 904.74396
B27: FY2032 operating NWC | D27: =D19*Scenarios!I49 -> 5219.1823 | E27: =E19*Scenarios!I49 -> 5244.8925 | F27: =F19*Scenarios!I49 -> 5270.6028 | G27: =G19*Scenarios!I49 -> 5296.313 | H27: =H19*Scenarios!I49 -> 5322.0233
B28: FY2032 change in operating NWC | D28: =D27-Scenarios!I50 -> 77.130772 | E28: =E27-Scenarios!I50 -> 102.84103 | F28: =F27-Scenarios!I50 -> 128.55129 | G28: =G27-Scenarios!I50 -> 154.26154 | H28: =H27-Scenarios!I50 -> 179.9718
B29: FY2032 FCFF | D29: =D24+D25-D26-D28 -> 4818.4622 | E29: =E24+E25-E26-E28 -> 4816.8682 | F29: =F24+F25-F26-F28 -> 4815.2741 | G29: =G24+G25-G26-G28 -> 4813.6801 | H29: =H24+H25-H26-H28 -> 4812.0861
B30: FY2032 EBITDA proxy | D30: =D22+D25 -> 7098.0879 | E30: =E22+E25 -> 7133.0538 | F30: =F22+F25 -> 7168.0198 | G30: =G22+G25 -> 7202.9857 | H30: =H22+H25 -> 7237.9517

Sheet Checks
B2: Model checks
B3: Mechanical integrity, approved-snapshot reconciliation, warnings, and package/build controls remain distinct
A5: Mechanical integrity | C5: Approved snapshot | E5: Warnings | G5: Package/build controls | H5: Canonical publication gate
A6: =IF(COUNTIF(B9:B202,"Mechanical integrity")=0,"UNVERIFIED",IF(COUNTIFS(B9:B202,"Mechanical integrity",H9:H202,"FAIL")>0,"FAIL",IF(COUNTIFS(B9:B202,"Mechanical integrity",H9:H202,"<>PASS")>0,"UNVERIFIED","PASS"))) -> PASS | C6: =IF(COUNTIF(B9:B202,"Approved snapshot")=0,"UNVERIFIED",IF(COUNTIFS(B9:B202,"Approved snapshot",H9:H202,"DIFFERS FROM APPROVED")>0,"DIFFERS FROM APPROVED",IF(COUNTIFS(B9:B202,"Approved snapshot",H9:H202,"<>MATCHES APPROVED")>0,"UNVERIFIED","MATCHES APPROVED"))) -> MATCHES APPROVED | E6: =IF(COUNTIF(B9:B202,"*warning")=0,"UNVERIFIED",IF(COUNTIFS(B9:B202,"*warning",H9:H202,"*WARNING*")>0,"WARNINGS PRESENT",IF(COUNTIFS(B9:B202,"*warning",H9:H202,"<>PASS")>0,"UNVERIFIED","PASS"))) -> WARNINGS PRESENT | G6: =IF(COUNTIF(B9:B202,"Package/build control")=0,"UNVERIFIED",IF(COUNTIFS(B9:B202,"Package/build control",H9:H202,"FAIL")>0,"FAIL",IF(COUNTIFS(B9:B202,"Package/build control",H9:H202,"<>PASS")>0,"UNVERIFIED","PASS"))) -> PASS | H6: =IF(OR(A6="FAIL",G6="FAIL"),"FAIL",IF(OR(A6<>"PASS",G6<>"PASS"),"UNVERIFIED",IF(C6="DIFFERS FROM APPROVED","NOT PUBLISHABLE — DIFFERS FROM APPROVED",IF(C6<>"MATCHES APPROVED","UNVERIFIED",IF(E6="WARNINGS PRESENT","PASS WITH WARNINGS",IF(E6="PASS","PASS","UNVERIFIED")))))) -> PASS WITH WARNINGS
A8: Check ID | B8: Control class | C8: Category / scope | D8: Actual | E8: Expected | F8: Difference | G8: Tolerance | H8: Status | I8: Notes / fix location
A9: desktop_excel_recalculation_sentinel | B9: Package/build control | C9: recalculation — workbook | D9: =1+1 -> 2 | E9: 2 | F9: =D9-E9 -> 0 | G9: 0 | H9: =IF(AND(ISNUMBER(D9),ISNUMBER(E9),ISNUMBER(F9),ISNUMBER(G9)),IF(ABS(F9)<=G9,"PASS","FAIL"),"UNVERIFIED") -> PASS | I9: Seeded incorrectly before COM; must equal 2 only after desktop Excel recalculation.
A10: valuation_input_count | B10: Package/build control | C10: inputs — workbook | D10: =COUNTA(Sources!A7:A40) -> 34 | E10: 34 | F10: =D10-E10 -> 0 | G10: 0 | H10: =IF(AND(ISNUMBER(D10),ISNUMBER(E10),ISNUMBER(F10),ISNUMBER(G10)),IF(ABS(F10)<=G10,"PASS","FAIL"),"UNVERIFIED") -> PASS | I10: Sources!A7:A40
A11: valuation_inputs_approved | B11: Package/build control | C11: inputs — workbook | D11: =COUNTIF(Sources!I7:I40,"approved") -> 34 | E11: 34 | F11: =D11-E11 -> 0 | G11: 0 | H11: =IF(AND(ISNUMBER(D11),ISNUMBER(E11),ISNUMBER(F11),ISNUMBER(G11)),IF(ABS(F11)<=G11,"PASS","FAIL"),"UNVERIFIED") -> PASS | I11: Sources!I7:I40
A12: valuation_source_count | B12: Package/build control | C12: sources — workbook | D12: =COUNTA(Sources!A45:A55) -> 11 | E12: 11 | F12: =D12-E12 -> 0 | G12: 0 | H12: =IF(AND(ISNUMBER(D12),ISNUMBER(E12),ISNUMBER(F12),ISNUMBER(G12)),IF(ABS(F12)<=G12,"PASS","FAIL"),"UNVERIFIED") -> PASS | I12: Sources!A45:A55
A13: scenario_assumption_count | B13: Package/build control | C13: inputs — workbook | D13: =COUNTA(Sources!A60:A164) -> 105 | E13: 105 | F13: =D13-E13 -> 0 | G13: 0 | H13: =IF(AND(ISNUMBER(D13),ISNUMBER(E13),ISNUMBER(F13),ISNUMBER(G13)),IF(ABS(F13)<=G13,"PASS","FAIL"),"UNVERIFIED") -> PASS | I13: Sources!A60:A164
A14: scenario_assumptions_approved | B14: Package/build control | C14: inputs — workbook | D14: =COUNTIF(Sources!J60:J164,"approved") -> 105 | E14: 105 | F14: =D14-E14 -> 0 | G14: 0 | H14: =IF(AND(ISNUMBER(D14),ISNUMBER(E14),ISNUMBER(F14),ISNUMBER(G14)),IF(ABS(F14)<=G14,"PASS","FAIL"),"UNVERIFIED") -> PASS | I14: Sources!J60:J164
A15: valuation_source_id_syntax | B15: Package/build control | C15: sources — valuation source register | D15: =SUMPRODUCT(--(LEN(Sources!A45:A55)=4),--(LEFT(Sources!A45:A55,2)="VS"),--ISNUMBER(FIND(MID(Sources!A45:A55,3,1),"0123456789")),--ISNUMBER(FIND(RIGHT(Sources!A45:A55,1),"0123456789"))) -> 11 | E15: 11 | F15: =D15-E15 -> 0 | G15: 0 | H15: =IF(AND(ISNUMBER(D15),ISNUMBER(E15),ISNUMBER(F15),ISNUMBER(G15)),IF(ABS(F15)<=G15,"PASS","FAIL"),"UNVERIFIED") -> PASS | I15: Every source-register ID follows VS plus exactly two ASCII digits.
A16: valuation_source_id_resolution | B16: Package/build control | C16: sources — valuation inputs | D16: =SUMPRODUCT(--(LEN(TRIM(Sources!G7:G40))>0),--(LEFT(SUBSTITUTE(SUBSTITUTE(TRIM(Sources!G7:G40)," ;",";"),"; ",";"),1)<>";"),--(RIGHT(SUBSTITUTE(SUBSTITUTE(TRIM(Sources!G7:G40)," ;",";"),"; ",";"),1)<>";"),--ISERROR(SEARCH(";;",SUBSTITUTE(SUBSTITUTE(TRIM(Sources!G7:G40)," ;",";"),"; ",";"))),--(SUBSTITUTE(SUBSTITUTE(SUBSTITUTE(SUBSTITUTE(SUBSTITUTE(SUBSTITUTE(SUBSTITUTE(SUBSTITUTE(SUBSTITUTE(SUBSTITUTE(SUBSTITUTE(";"&SUBSTITUTE(SUBSTITUTE(SUBSTITUTE(TRIM(Sources!G7:G40)," ;",";"),"; ",";"),";",";;")&";",";"&Sources!$A$45&";",""),";"&Sources!$A$46&";",""),";"&Sources!$A$47&";",""),";"&Sources!$A$48&";",""),";"&Sources!$A$49&";",""),";"&Sources!$A$50&";",""),";"&Sources!$A$51&";",""),";"&Sources!$A$52&";",""),";"&Sources!$A$53&";",""),";"&Sources!$A$54&";",""),";"&Sources!$A$55&";","")="")) -> 34 | E16: 34 | F16: =D16-E16 -> 0 | G16: 0 | H16: =IF(AND(ISNUMBER(D16),ISNUMBER(E16),ISNUMBER(F16),ISNUMBER(G16)),IF(ABS(F16)<=G16,"PASS","FAIL"),"UNVERIFIED") -> PASS | I16: Every semicolon-delimited VS## token resolves by exact boundary in tblValuationSources.
A17: scenario_source_id_resolution | B17: Package/build control | C17: sources — scenario assumptions | D17: =SUMPRODUCT(--ISNUMBER(MATCH(Sources!H60:H164,{"FS01","FS02","FS03","FS04","FS05","FS06"},0))) -> 105 | E17: 105 | F17: =D17-E17 -> 0 | G17: 0 | H17: =IF(AND(ISNUMBER(D17),ISNUMBER(E17),ISNUMBER(F17),ISNUMBER(G17)),IF(ABS(F17)<=G17,"PASS","FAIL"),"UNVERIFIED") -> PASS | I17: Every scenario source ID resolves to the committed Phase 4 forecast-source register.
A18: valuation_input_values_match_approved | B18: Approved snapshot | C18: inputs — valuation assumptions | D18: =--AND(Sources!D7=DATE(2026,9,4),Sources!D8=DATE(2026,9,4),Sources!D9=38.4,Sources!D10=281.387752,Sources!D11=1202.110951,Sources!D12=1.2,Sources!D13=7563,Sources!D14=1464,Sources!D15=6800,Sources!D16=7942,Sources!D17=0.3,Sources!D18=3091,Sources!D19=0.0478,Sources!D20=0.0414,Sources!D21=0.0078,Sources!D22=0.21,Sources!D23=30538,Sources!D24=13497,Sources!D25=2220,Sources!D26=143,Sources!D27=1,Sources!D28=0.79,Sources!D29=0.74,Sources!D30=0.025,Sources!D31=-0.01,Sources!D32=-0.005,Sources!D33=0,Sources!D34=0.005,Sources!D35=0.01,Sources!D36=0.015,Sources!D37=0.02,Sources!D38=0.025,Sources!D39=0.03,Sources!D40=0.035) -> 1 | E18: 1 | F18: =D18-E18 -> 0 | G18: 0 | H18: =IF(AND(ISNUMBER(D18),ISNUMBER(E18),ISNUMBER(F18),ISNUMBER(G18)),IF(ABS(F18)<=G18,"MATCHES APPROVED","DIFFERS FROM APPROVED"),"UNVERIFIED") -> MATCHES APPROVED | I18: Editable valuation values reconcile to the approved committed snapshot.
A19: scenario_input_values_match_approved | B19: Approved snapshot | C19: inputs — scenario assumptions | D19: =--AND(Sources!D60=-0.02,Sources!D61=0.425,Sources!D62=0.352,Sources!D63=0.21,Sources!D64=0.016,Sources!D65=0.015,Sources!D66=0.111,Sources!D67=0.02,Sources!D68=0.432,Sources!D69=0.345,Sources!D70=0.21,Sources!D71=0.016,Sources!D72=0.016,Sources!D73=0.108,Sources!D74=0.035,Sources!D75=0.44,Sources!D76=0.338,Sources!D77=0.21,Sources!D78=0.016,Sources!D79=0.017,Sources!D80=0.105,Sources!D81=0.04,Sources!D82=0.445,Sources!D83=0.332,Sources!D84=0.21,Sources!D85=0.016,Sources!D86=0.017,Sources!D87=0.102,Sources!D88=0.03,Sources!D89=0.448,Sources!D90=0.328,Sources!D91=0.21,Sources!D92=0.016,Sources!D93=0.017,Sources!D94=0.1,Sources!D95=0.005,Sources!D96=0.43,Sources!D97=0.348,Sources!D98=0.21,Sources!D99=0.016,Sources!D100=0.017,Sources!D101=0.108,Sources!D102=0.04,Sources!D103=0.44,Sources!D104=0.34,Sources!D105=0.21,Sources!D106=0.016,Sources!D107=0.018,Sources!D108=0.104,Sources!D109=0.05,Sources!D110=0.45,Sources!D111=0.33,Sources!D112=0.21,Sources!D113=0.016,Sources!D114=0.019,Sources!D115=0.1,Sources!D116=0.05,Sources!D117=0.455,Sources!D118=0.322,Sources!D119=0.21,Sources!D120=0.017,Sources!D121=0.019,Sources!D122=0.097,Sources!D123=0.035,Sources!D124=0.458,Sources!D125=0.318,Sources!D126=0.21,Sources!D127=0.017,Sources!D128=0.018,Sources!D129=0.095,Sources!D130=-0.04,Sources!D131=0.415,Sources!D132=0.355,Sources!D133=0.21,Sources!D134=0.016,Sources!D135=0.013,Sources!D136=0.117,Sources!D137=-0.01,Sources!D138=0.415,Sources!D139=0.357,Sources!D140=0.21,Sources!D141=0.016,Sources!D142=0.013,Sources!D143=0.118,Sources!D144=0.01,Sources!D145=0.42,Sources!D146=0.354,Sources!D147=0.21,Sources!D148=0.016,Sources!D149=0.014,Sources!D150=0.118,Sources!D151=0.02,Sources!D152=0.425,Sources!D153=0.35,Sources!D154=0.21,Sources!D155=0.015,Sources!D156=0.015,Sources!D157=0.117,Sources!D158=0.02,Sources!D159=0.428,Sources!D160=0.346,Sources!D161=0.21,Sources!D162=0.015,Sources!D163=0.015,Sources!D164=0.115) -> 1 | E19: 1 | F19: =D19-E19 -> 0 | G19: 0 | H19: =IF(AND(ISNUMBER(D19),ISNUMBER(E19),ISNUMBER(F19),ISNUMBER(G19)),IF(ABS(F19)<=G19,"MATCHES APPROVED","DIFFERS FROM APPROVED"),"UNVERIFIED") -> MATCHES APPROVED | I19: Editable scenario values reconcile to the approved committed snapshot.
A20: wacc_weights_sum | B20: Mechanical integrity | C20: wacc — primary | D20: =WACC!E34+WACC!E35 -> 1 | E20: 1 | F20: =D20-E20 -> 0 | G20: 1e-12 | H20: =IF(AND(ISNUMBER(D20),ISNUMBER(E20),ISNUMBER(F20),ISNUMBER(G20)),IF(ABS(F20)<=G20,"PASS","FAIL"),"UNVERIFIED") -> PASS | I20: WACC primary weights
A21: unlevered_beta_formula | B21: Approved snapshot | C21: wacc — primary | D21: =WACC!E23 -> 0.9262443 | E21: 0.9262443 | F21: =D21-E21 -> 0 | G21: 1e-09 | H21: =IF(AND(ISNUMBER(D21),ISNUMBER(E21),ISNUMBER(F21),ISNUMBER(G21)),IF(ABS(F21)<=G21,"MATCHES APPROVED","DIFFERS FROM APPROVED"),"UNVERIFIED") -> MATCHES APPROVED | I21: WACC product-revenue-weighted beta
A22: relevered_beta_formula | B22: Approved snapshot | C22: wacc — primary | D22: =WACC!E27 -> 1.0135903 | E22: 1.0135903 | F22: =D22-E22 -> 0 | G22: 1e-09 | H22: =IF(AND(ISNUMBER(D22),ISNUMBER(E22),ISNUMBER(F22),ISNUMBER(G22)),IF(ABS(F22)<=G22,"MATCHES APPROVED","DIFFERS FROM APPROVED"),"UNVERIFIED") -> MATCHES APPROVED | I22: WACC relevering equation
A23: capm_cost_of_equity | B23: Approved snapshot | C23: wacc — primary | D23: =WACC!E30 -> 0.089762639 | E23: 0.089762639 | F23: =D23-E23 -> 0 | G23: 1e-09 | H23: =IF(AND(ISNUMBER(D23),ISNUMBER(E23),ISNUMBER(F23),ISNUMBER(G23)),IF(ABS(F23)<=G23,"MATCHES APPROVED","DIFFERS FROM APPROVED"),"UNVERIFIED") -> MATCHES APPROVED | I23: WACC CAPM equation
A24: pretax_cost_of_debt | B24: Approved snapshot | C24: wacc — primary | D24: =WACC!E32 -> 0.0556 | E24: 0.0556 | F24: =D24-E24 -> 0 | G24: 1e-09 | H24: =IF(AND(ISNUMBER(D24),ISNUMBER(E24),ISNUMBER(F24),ISNUMBER(G24)),IF(ABS(F24)<=G24,"MATCHES APPROVED","DIFFERS FROM APPROVED"),"UNVERIFIED") -> MATCHES APPROVED | I24: Risk-free rate plus default spread
A25: after_tax_cost_of_debt | B25: Approved snapshot | C25: wacc — primary | D25: =WACC!E33 -> 0.043924 | E25: 0.043924 | F25: =D25-E25 -> 0 | G25: 1e-09 | H25: =IF(AND(ISNUMBER(D25),ISNUMBER(E25),ISNUMBER(F25),ISNUMBER(G25)),IF(ABS(F25)<=G25,"MATCHES APPROVED","DIFFERS FROM APPROVED"),"UNVERIFIED") -> MATCHES APPROVED | I25: Pretax debt cost after operating-tax shield
A26: wacc_formula | B26: Approved snapshot | C26: wacc — primary | D26: =WACC!E36 -> 0.084874438 | E26: 0.084874438 | F26: =D26-E26 -> 0 | G26: 1e-09 | H26: =IF(AND(ISNUMBER(D26),ISNUMBER(E26),ISNUMBER(F26),ISNUMBER(G26)),IF(ABS(F26)<=G26,"MATCHES APPROVED","DIFFERS FROM APPROVED"),"UNVERIFIED") -> MATCHES APPROVED | I26: WACC!E calculated result
A27: wacc_carrying_crosscheck | B27: Approved snapshot | C27: wacc — carrying debt | D27: =WACC!J36 -> 0.084686944 | E27: 0.084686944 | F27: =D27-E27 -> 0 | G27: 1e-09 | H27: =IF(AND(ISNUMBER(D27),ISNUMBER(E27),ISNUMBER(F27),ISNUMBER(G27)),IF(ABS(F27)<=G27,"MATCHES APPROVED","DIFFERS FROM APPROVED"),"UNVERIFIED") -> MATCHES APPROVED | I27: WACC!J calculated result
A28: wacc_exceeds_terminal_growth | B28: Mechanical integrity | C28: terminal value — workbook | D28: =--(CalculatedWACC>TerminalGrowth) -> 1 | E28: 1 | F28: =D28-E28 -> 0 | G28: 0 | H28: =IF(AND(ISNUMBER(D28),ISNUMBER(E28),ISNUMBER(F28),ISNUMBER(G28)),IF(ABS(F28)<=G28,"PASS","FAIL"),"UNVERIFIED") -> PASS | I28: Headline WACC must exceed headline terminal growth.
A29: forecast_bear_FY2027_revenue | B29: Approved snapshot | C29: forecast reconciliation — bear | D29: =Scenarios!E10 -> 44542.08 | E29: 44542.08 | F29: =D29-E29 -> 0 | G29: 0.1 | H29: =IF(AND(ISNUMBER(D29),ISNUMBER(E29),ISNUMBER(F29),ISNUMBER(G29)),IF(ABS(F29)<=G29,"MATCHES APPROVED","DIFFERS FROM APPROVED"),"UNVERIFIED") -> MATCHES APPROVED | I29: Scenarios!E10
A30: forecast_bear_FY2027_derived_operating_income | B30: Approved snapshot | C30: forecast reconciliation — bear | D30: =Scenarios!E15 -> 2672.5248 | E30: 2672.5248 | F30: =D30-E30 -> 0 | G30: 0.1 | H30: =IF(AND(ISNUMBER(D30),ISNUMBER(E30),ISNUMBER(F30),ISNUMBER(G30)),IF(ABS(F30)<=G30,"MATCHES APPROVED","DIFFERS FROM APPROVED"),"UNVERIFIED") -> MATCHES APPROVED | I30: Scenarios!E15
A31: forecast_bear_FY2027_operating_nwc_proxy | B31: Approved snapshot | C31: forecast reconciliation — bear | D31: =Scenarios!E25 -> 5211.4234 | E31: 5211.4234 | F31: =D31-E31 -> 0 | G31: 0.1 | H31: =IF(AND(ISNUMBER(D31),ISNUMBER(E31),ISNUMBER(F31),ISNUMBER(G31)),IF(ABS(F31)<=G31,"MATCHES APPROVED","DIFFERS FROM APPROVED"),"UNVERIFIED") -> MATCHES APPROVED | I31: Scenarios!E25
A32: forecast_bear_FY2027_fcff | B32: Approved snapshot | C32: forecast reconciliation — bear | D32: =Scenarios!E27 -> 2540.4975 | E32: 2540.4975 | F32: =D32-E32 -> 0 | G32: 0.1 | H32: =IF(AND(ISNUMBER(D32),ISNUMBER(E32),ISNUMBER(F32),ISNUMBER(G32)),IF(ABS(F32)<=G32,"MATCHES APPROVED","DIFFERS FROM APPROVED"),"UNVERIFIED") -> MATCHES APPROVED | I32: Scenarios!E27
A33: fcff_identity_bear_FY2027 | B33: Mechanical integrity | C33: FCFF — bear | D33: =Scenarios!E27-(Scenarios!E19+Scenarios!E21-Scenarios!E23-Scenarios!E26) -> 0 | E33: 0 | F33: =D33-E33 -> 0 | G33: 1e-07 | H33: =IF(AND(ISNUMBER(D33),ISNUMBER(E33),ISNUMBER(F33),ISNUMBER(G33)),IF(ABS(F33)<=G33,"PASS","FAIL"),"UNVERIFIED") -> PASS | I33: Scenarios!E27 equals NOPAT + D&A - capex - change in operating NWC.
A34: forecast_bear_FY2028_revenue | B34: Approved snapshot | C34: forecast reconciliation — bear | D34: =Scenarios!F10 -> 44096.659 | E34: 44096.659 | F34: =D34-E34 -> 0 | G34: 0.1 | H34: =IF(AND(ISNUMBER(D34),ISNUMBER(E34),ISNUMBER(F34),ISNUMBER(G34)),IF(ABS(F34)<=G34,"MATCHES APPROVED","DIFFERS FROM APPROVED"),"UNVERIFIED") -> MATCHES APPROVED | I34: Scenarios!F10
A35: forecast_bear_FY2028_derived_operating_income | B35: Approved snapshot | C35: forecast reconciliation — bear | D35: =Scenarios!F15 -> 2557.6062 | E35: 2557.6062 | F35: =D35-E35 -> 0 | G35: 0.1 | H35: =IF(AND(ISNUMBER(D35),ISNUMBER(E35),ISNUMBER(F35),ISNUMBER(G35)),IF(ABS(F35)<=G35,"MATCHES APPROVED","DIFFERS FROM APPROVED"),"UNVERIFIED") -> MATCHES APPROVED | I35: Scenarios!F15
A36: forecast_bear_FY2028_operating_nwc_proxy | B36: Approved snapshot | C36: forecast reconciliation — bear | D36: =Scenarios!F25 -> 5203.4058 | E36: 5203.4058 | F36: =D36-E36 -> 0 | G36: 0.1 | H36: =IF(AND(ISNUMBER(D36),ISNUMBER(E36),ISNUMBER(F36),ISNUMBER(G36)),IF(ABS(F36)<=G36,"MATCHES APPROVED","DIFFERS FROM APPROVED"),"UNVERIFIED") -> MATCHES APPROVED | I36: Scenarios!F25
A37: forecast_bear_FY2028_fcff | B37: Approved snapshot | C37: forecast reconciliation — bear | D37: =Scenarios!F27 -> 2160.8165 | E37: 2160.8165 | F37: =D37-E37 -> 0 | G37: 0.1 | H37: =IF(AND(ISNUMBER(D37),ISNUMBER(E37),ISNUMBER(F37),ISNUMBER(G37)),IF(ABS(F37)<=G37,"MATCHES APPROVED","DIFFERS FROM APPROVED"),"UNVERIFIED") -> MATCHES APPROVED | I37: Scenarios!F27
A38: fcff_identity_bear_FY2028 | B38: Mechanical integrity | C38: FCFF — bear | D38: =Scenarios!F27-(Scenarios!F19+Scenarios!F21-Scenarios!F23-Scenarios!F26) -> 0 | E38: 0 | F38: =D38-E38 -> 0 | G38: 1e-07 | H38: =IF(AND(ISNUMBER(D38),ISNUMBER(E38),ISNUMBER(F38),ISNUMBER(G38)),IF(ABS(F38)<=G38,"PASS","FAIL"),"UNVERIFIED") -> PASS | I38: Scenarios!F27 equals NOPAT + D&A - capex - change in operating NWC.
A39: forecast_bear_FY2029_revenue | B39: Approved snapshot | C39: forecast reconciliation — bear | D39: =Scenarios!G10 -> 44537.626 | E39: 44537.626 | F39: =D39-E39 -> 0 | G39: 0.1 | H39: =IF(AND(ISNUMBER(D39),ISNUMBER(E39),ISNUMBER(F39),ISNUMBER(G39)),IF(ABS(F39)<=G39,"MATCHES APPROVED","DIFFERS FROM APPROVED"),"UNVERIFIED") -> MATCHES APPROVED | I39: Scenarios!G10
A40: forecast_bear_FY2029_derived_operating_income | B40: Approved snapshot | C40: forecast reconciliation — bear | D40: =Scenarios!G15 -> 2939.4833 | E40: 2939.4833 | F40: =D40-E40 -> 0 | G40: 0.1 | H40: =IF(AND(ISNUMBER(D40),ISNUMBER(E40),ISNUMBER(F40),ISNUMBER(G40)),IF(ABS(F40)<=G40,"MATCHES APPROVED","DIFFERS FROM APPROVED"),"UNVERIFIED") -> MATCHES APPROVED | I40: Scenarios!G15
A41: forecast_bear_FY2029_operating_nwc_proxy | B41: Approved snapshot | C41: forecast reconciliation — bear | D41: =Scenarios!G25 -> 5255.4398 | E41: 5255.4398 | F41: =D41-E41 -> 0 | G41: 0.1 | H41: =IF(AND(ISNUMBER(D41),ISNUMBER(E41),ISNUMBER(F41),ISNUMBER(G41)),IF(ABS(F41)<=G41,"MATCHES APPROVED","DIFFERS FROM APPROVED"),"UNVERIFIED") -> MATCHES APPROVED | I41: Scenarios!G25
A42: forecast_bear_FY2029_fcff | B42: Approved snapshot | C42: forecast reconciliation — bear | D42: =Scenarios!G27 -> 2359.233 | E42: 2359.233 | F42: =D42-E42 -> 0 | G42: 0.1 | H42: =IF(AND(ISNUMBER(D42),ISNUMBER(E42),ISNUMBER(F42),ISNUMBER(G42)),IF(ABS(F42)<=G42,"MATCHES APPROVED","DIFFERS FROM APPROVED"),"UNVERIFIED") -> MATCHES APPROVED | I42: Scenarios!G27
A43: fcff_identity_bear_FY2029 | B43: Mechanical integrity | C43: FCFF — bear | D43: =Scenarios!G27-(Scenarios!G19+Scenarios!G21-Scenarios!G23-Scenarios!G26) -> 0 | E43: 0 | F43: =D43-E43 -> 0 | G43: 1e-07 | H43: =IF(AND(ISNUMBER(D43),ISNUMBER(E43),ISNUMBER(F43),ISNUMBER(G43)),IF(ABS(F43)<=G43,"PASS","FAIL"),"UNVERIFIED") -> PASS | I43: Scenarios!G27 equals NOPAT + D&A - capex - change in operating NWC.
A44: forecast_bear_FY2030_revenue | B44: Approved snapshot | C44: forecast reconciliation — bear | D44: =Scenarios!H10 -> 45428.378 | E44: 45428.378 | F44: =D44-E44 -> 0 | G44: 0.1 | H44: =IF(AND(ISNUMBER(D44),ISNUMBER(E44),ISNUMBER(F44),ISNUMBER(G44)),IF(ABS(F44)<=G44,"MATCHES APPROVED","DIFFERS FROM APPROVED"),"UNVERIFIED") -> MATCHES APPROVED | I44: Scenarios!H10
A45: forecast_bear_FY2030_derived_operating_income | B45: Approved snapshot | C45: forecast reconciliation — bear | D45: =Scenarios!H15 -> 3407.1284 | E45: 3407.1284 | F45: =D45-E45 -> 0 | G45: 0.1 | H45: =IF(AND(ISNUMBER(D45),ISNUMBER(E45),ISNUMBER(F45),ISNUMBER(G45)),IF(ABS(F45)<=G45,"MATCHES APPROVED","DIFFERS FROM APPROVED"),"UNVERIFIED") -> MATCHES APPROVED | I45: Scenarios!H15
A46: forecast_bear_FY2030_operating_nwc_proxy | B46: Approved snapshot | C46: forecast reconciliation — bear | D46: =Scenarios!H25 -> 5315.1203 | E46: 5315.1203 | F46: =D46-E46 -> 0 | G46: 0.1 | H46: =IF(AND(ISNUMBER(D46),ISNUMBER(E46),ISNUMBER(F46),ISNUMBER(G46)),IF(ABS(F46)<=G46,"MATCHES APPROVED","DIFFERS FROM APPROVED"),"UNVERIFIED") -> MATCHES APPROVED | I46: Scenarios!H25
A47: forecast_bear_FY2030_fcff | B47: Approved snapshot | C47: forecast reconciliation — bear | D47: =Scenarios!H27 -> 2631.951 | E47: 2631.951 | F47: =D47-E47 -> 0 | G47: 0.1 | H47: =IF(AND(ISNUMBER(D47),ISNUMBER(E47),ISNUMBER(F47),ISNUMBER(G47)),IF(ABS(F47)<=G47,"MATCHES APPROVED","DIFFERS FROM APPROVED"),"UNVERIFIED") -> MATCHES APPROVED | I47: Scenarios!H27
A48: fcff_identity_bear_FY2030 | B48: Mechanical integrity | C48: FCFF — bear | D48: =Scenarios!H27-(Scenarios!H19+Scenarios!H21-Scenarios!H23-Scenarios!H26) -> 0 | E48: 0 | F48: =D48-E48 -> 0 | G48: 1e-07 | H48: =IF(AND(ISNUMBER(D48),ISNUMBER(E48),ISNUMBER(F48),ISNUMBER(G48)),IF(ABS(F48)<=G48,"PASS","FAIL"),"UNVERIFIED") -> PASS | I48: Scenarios!H27 equals NOPAT + D&A - capex - change in operating NWC.
A49: forecast_bear_FY2031_revenue | B49: Approved snapshot | C49: forecast reconciliation — bear | D49: =Scenarios!I10 -> 46336.946 | E49: 46336.946 | F49: =D49-E49 -> 0 | G49: 0.1 | H49: =IF(AND(ISNUMBER(D49),ISNUMBER(E49),ISNUMBER(F49),ISNUMBER(G49)),IF(ABS(F49)<=G49,"MATCHES APPROVED","DIFFERS FROM APPROVED"),"UNVERIFIED") -> MATCHES APPROVED | I49: Scenarios!I10
A50: forecast_bear_FY2031_derived_operating_income | B50: Approved snapshot | C50: forecast reconciliation — bear | D50: =Scenarios!I15 -> 3799.6296 | E50: 3799.6296 | F50: =D50-E50 -> 0 | G50: 0.1 | H50: =IF(AND(ISNUMBER(D50),ISNUMBER(E50),ISNUMBER(F50),ISNUMBER(G50)),IF(ABS(F50)<=G50,"MATCHES APPROVED","DIFFERS FROM APPROVED"),"UNVERIFIED") -> MATCHES APPROVED | I50: Scenarios!I15
A51: forecast_bear_FY2031_operating_nwc_proxy | B51: Approved snapshot | C51: forecast reconciliation — bear | D51: =Scenarios!I25 -> 5328.7488 | E51: 5328.7488 | F51: =D51-E51 -> 0 | G51: 0.1 | H51: =IF(AND(ISNUMBER(D51),ISNUMBER(E51),ISNUMBER(F51),ISNUMBER(G51)),IF(ABS(F51)<=G51,"MATCHES APPROVED","DIFFERS FROM APPROVED"),"UNVERIFIED") -> MATCHES APPROVED | I51: Scenarios!I25
A52: forecast_bear_FY2031_fcff | B52: Approved snapshot | C52: forecast reconciliation — bear | D52: =Scenarios!I27 -> 2988.0788 | E52: 2988.0788 | F52: =D52-E52 -> 0 | G52: 0.1 | H52: =IF(AND(ISNUMBER(D52),ISNUMBER(E52),ISNUMBER(F52),ISNUMBER(G52)),IF(ABS(F52)<=G52,"MATCHES APPROVED","DIFFERS FROM APPROVED"),"UNVERIFIED") -> MATCHES APPROVED | I52: Scenarios!I27
A53: fcff_identity_bear_FY2031 | B53: Mechanical integrity | C53: FCFF — bear | D53: =Scenarios!I27-(Scenarios!I19+Scenarios!I21-Scenarios!I23-Scenarios!I26) -> 0 | E53: 0 | F53: =D53-E53 -> 0 | G53: 1e-07 | H53: =IF(AND(ISNUMBER(D53),ISNUMBER(E53),ISNUMBER(F53),ISNUMBER(G53)),IF(ABS(F53)<=G53,"PASS","FAIL"),"UNVERIFIED") -> PASS | I53: Scenarios!I27 equals NOPAT + D&A - capex - change in operating NWC.
A54: forecast_base_FY2027_revenue | B54: Approved snapshot | C54: forecast reconciliation — base | D54: =Scenarios!E35 -> 45470.04 | E54: 45470.04 | F54: =D54-E54 -> 0 | G54: 0.1 | H54: =IF(AND(ISNUMBER(D54),ISNUMBER(E54),ISNUMBER(F54),ISNUMBER(G54)),IF(ABS(F54)<=G54,"MATCHES APPROVED","DIFFERS FROM APPROVED"),"UNVERIFIED") -> MATCHES APPROVED | I54: Scenarios!E35
A55: forecast_base_FY2027_derived_operating_income | B55: Approved snapshot | C55: forecast reconciliation — base | D55: =Scenarios!E40 -> 3319.3129 | E55: 3319.3129 | F55: =D55-E55 -> 0 | G55: 0.1 | H55: =IF(AND(ISNUMBER(D55),ISNUMBER(E55),ISNUMBER(F55),ISNUMBER(G55)),IF(ABS(F55)<=G55,"MATCHES APPROVED","DIFFERS FROM APPROVED"),"UNVERIFIED") -> MATCHES APPROVED | I55: Scenarios!E40
A56: forecast_base_FY2027_operating_nwc_proxy | B56: Approved snapshot | C56: forecast reconciliation — base | D56: =Scenarios!E50 -> 5047.1744 | E56: 5047.1744 | F56: =D56-E56 -> 0 | G56: 0.1 | H56: =IF(AND(ISNUMBER(D56),ISNUMBER(E56),ISNUMBER(F56),ISNUMBER(G56)),IF(ABS(F56)<=G56,"MATCHES APPROVED","DIFFERS FROM APPROVED"),"UNVERIFIED") -> MATCHES APPROVED | I56: Scenarios!E50
A57: forecast_base_FY2027_fcff | B57: Approved snapshot | C57: forecast reconciliation — base | D57: =Scenarios!E52 -> 3127.5528 | E57: 3127.5528 | F57: =D57-E57 -> 0 | G57: 0.1 | H57: =IF(AND(ISNUMBER(D57),ISNUMBER(E57),ISNUMBER(F57),ISNUMBER(G57)),IF(ABS(F57)<=G57,"MATCHES APPROVED","DIFFERS FROM APPROVED"),"UNVERIFIED") -> MATCHES APPROVED | I57: Scenarios!E52
A58: fcff_identity_base_FY2027 | B58: Mechanical integrity | C58: FCFF — base | D58: =Scenarios!E52-(Scenarios!E44+Scenarios!E46-Scenarios!E48-Scenarios!E51) -> 0 | E58: 0 | F58: =D58-E58 -> 0 | G58: 1e-07 | H58: =IF(AND(ISNUMBER(D58),ISNUMBER(E58),ISNUMBER(F58),ISNUMBER(G58)),IF(ABS(F58)<=G58,"PASS","FAIL"),"UNVERIFIED") -> PASS | I58: Scenarios!E52 equals NOPAT + D&A - capex - change in operating NWC.
A59: forecast_base_FY2028_revenue | B59: Approved snapshot | C59: forecast reconciliation — base | D59: =Scenarios!F35 -> 46379.441 | E59: 46379.441 | F59: =D59-E59 -> 0 | G59: 0.1 | H59: =IF(AND(ISNUMBER(D59),ISNUMBER(E59),ISNUMBER(F59),ISNUMBER(G59)),IF(ABS(F59)<=G59,"MATCHES APPROVED","DIFFERS FROM APPROVED"),"UNVERIFIED") -> MATCHES APPROVED | I59: Scenarios!F35
A60: forecast_base_FY2028_derived_operating_income | B60: Approved snapshot | C60: forecast reconciliation — base | D60: =Scenarios!F40 -> 4035.0113 | E60: 4035.0113 | F60: =D60-E60 -> 0 | G60: 0.1 | H60: =IF(AND(ISNUMBER(D60),ISNUMBER(E60),ISNUMBER(F60),ISNUMBER(G60)),IF(ABS(F60)<=G60,"MATCHES APPROVED","DIFFERS FROM APPROVED"),"UNVERIFIED") -> MATCHES APPROVED | I60: Scenarios!F40
A61: forecast_base_FY2028_operating_nwc_proxy | B61: Approved snapshot | C61: forecast reconciliation — base | D61: =Scenarios!F50 -> 5008.9796 | E61: 5008.9796 | F61: =D61-E61 -> 0 | G61: 0.1 | H61: =IF(AND(ISNUMBER(D61),ISNUMBER(E61),ISNUMBER(F61),ISNUMBER(G61)),IF(ABS(F61)<=G61,"MATCHES APPROVED","DIFFERS FROM APPROVED"),"UNVERIFIED") -> MATCHES APPROVED | I61: Scenarios!F50
A62: forecast_base_FY2028_fcff | B62: Approved snapshot | C62: forecast reconciliation — base | D62: =Scenarios!F52 -> 3225.8538 | E62: 3225.8538 | F62: =D62-E62 -> 0 | G62: 0.1 | H62: =IF(AND(ISNUMBER(D62),ISNUMBER(E62),ISNUMBER(F62),ISNUMBER(G62)),IF(ABS(F62)<=G62,"MATCHES APPROVED","DIFFERS FROM APPROVED"),"UNVERIFIED") -> MATCHES APPROVED | I62: Scenarios!F52
A63: fcff_identity_base_FY2028 | B63: Mechanical integrity | C63: FCFF — base | D63: =Scenarios!F52-(Scenarios!F44+Scenarios!F46-Scenarios!F48-Scenarios!F51) -> 0 | E63: 0 | F63: =D63-E63 -> 0 | G63: 1e-07 | H63: =IF(AND(ISNUMBER(D63),ISNUMBER(E63),ISNUMBER(F63),ISNUMBER(G63)),IF(ABS(F63)<=G63,"PASS","FAIL"),"UNVERIFIED") -> PASS | I63: Scenarios!F52 equals NOPAT + D&A - capex - change in operating NWC.
A64: forecast_base_FY2029_revenue | B64: Approved snapshot | C64: forecast reconciliation — base | D64: =Scenarios!G35 -> 48002.721 | E64: 48002.721 | F64: =D64-E64 -> 0 | G64: 0.1 | H64: =IF(AND(ISNUMBER(D64),ISNUMBER(E64),ISNUMBER(F64),ISNUMBER(G64)),IF(ABS(F64)<=G64,"MATCHES APPROVED","DIFFERS FROM APPROVED"),"UNVERIFIED") -> MATCHES APPROVED | I64: Scenarios!G35
A65: forecast_base_FY2029_derived_operating_income | B65: Approved snapshot | C65: forecast reconciliation — base | D65: =Scenarios!G40 -> 4896.2776 | E65: 4896.2776 | F65: =D65-E65 -> 0 | G65: 0.1 | H65: =IF(AND(ISNUMBER(D65),ISNUMBER(E65),ISNUMBER(F65),ISNUMBER(G65)),IF(ABS(F65)<=G65,"MATCHES APPROVED","DIFFERS FROM APPROVED"),"UNVERIFIED") -> MATCHES APPROVED | I65: Scenarios!G40
A66: forecast_base_FY2029_operating_nwc_proxy | B66: Approved snapshot | C66: forecast reconciliation — base | D66: =Scenarios!G50 -> 5040.2857 | E66: 5040.2857 | F66: =D66-E66 -> 0 | G66: 0.1 | H66: =IF(AND(ISNUMBER(D66),ISNUMBER(E66),ISNUMBER(F66),ISNUMBER(G66)),IF(ABS(F66)<=G66,"MATCHES APPROVED","DIFFERS FROM APPROVED"),"UNVERIFIED") -> MATCHES APPROVED | I66: Scenarios!G50
A67: forecast_base_FY2029_fcff | B67: Approved snapshot | C67: forecast reconciliation — base | D67: =Scenarios!G52 -> 3788.7504 | E67: 3788.7504 | F67: =D67-E67 -> 0 | G67: 0.1 | H67: =IF(AND(ISNUMBER(D67),ISNUMBER(E67),ISNUMBER(F67),ISNUMBER(G67)),IF(ABS(F67)<=G67,"MATCHES APPROVED","DIFFERS FROM APPROVED"),"UNVERIFIED") -> MATCHES APPROVED | I67: Scenarios!G52
A68: fcff_identity_base_FY2029 | B68: Mechanical integrity | C68: FCFF — base | D68: =Scenarios!G52-(Scenarios!G44+Scenarios!G46-Scenarios!G48-Scenarios!G51) -> 0 | E68: 0 | F68: =D68-E68 -> 0 | G68: 1e-07 | H68: =IF(AND(ISNUMBER(D68),ISNUMBER(E68),ISNUMBER(F68),ISNUMBER(G68)),IF(ABS(F68)<=G68,"PASS","FAIL"),"UNVERIFIED") -> PASS | I68: Scenarios!G52 equals NOPAT + D&A - capex - change in operating NWC.
A69: forecast_base_FY2030_revenue | B69: Approved snapshot | C69: forecast reconciliation — base | D69: =Scenarios!H35 -> 49922.83 | E69: 49922.83 | F69: =D69-E69 -> 0 | G69: 0.1 | H69: =IF(AND(ISNUMBER(D69),ISNUMBER(E69),ISNUMBER(F69),ISNUMBER(G69)),IF(ABS(F69)<=G69,"MATCHES APPROVED","DIFFERS FROM APPROVED"),"UNVERIFIED") -> MATCHES APPROVED | I69: Scenarios!H35
A70: forecast_base_FY2030_derived_operating_income | B70: Approved snapshot | C70: forecast reconciliation — base | D70: =Scenarios!H40 -> 5641.2798 | E70: 5641.2798 | F70: =D70-E70 -> 0 | G70: 0.1 | H70: =IF(AND(ISNUMBER(D70),ISNUMBER(E70),ISNUMBER(F70),ISNUMBER(G70)),IF(ABS(F70)<=G70,"MATCHES APPROVED","DIFFERS FROM APPROVED"),"UNVERIFIED") -> MATCHES APPROVED | I70: Scenarios!H40
A71: forecast_base_FY2030_operating_nwc_proxy | B71: Approved snapshot | C71: forecast reconciliation — base | D71: =Scenarios!H50 -> 5092.1287 | E71: 5092.1287 | F71: =D71-E71 -> 0 | G71: 0.1 | H71: =IF(AND(ISNUMBER(D71),ISNUMBER(E71),ISNUMBER(F71),ISNUMBER(G71)),IF(ABS(F71)<=G71,"MATCHES APPROVED","DIFFERS FROM APPROVED"),"UNVERIFIED") -> MATCHES APPROVED | I71: Scenarios!H50
A72: forecast_base_FY2030_fcff | B72: Approved snapshot | C72: forecast reconciliation — base | D72: =Scenarios!H52 -> 4354.8453 | E72: 4354.8453 | F72: =D72-E72 -> 0 | G72: 0.1 | H72: =IF(AND(ISNUMBER(D72),ISNUMBER(E72),ISNUMBER(F72),ISNUMBER(G72)),IF(ABS(F72)<=G72,"MATCHES APPROVED","DIFFERS FROM APPROVED"),"UNVERIFIED") -> MATCHES APPROVED | I72: Scenarios!H52
A73: fcff_identity_base_FY2030 | B73: Mechanical integrity | C73: FCFF — base | D73: =Scenarios!H52-(Scenarios!H44+Scenarios!H46-Scenarios!H48-Scenarios!H51) -> 0 | E73: 0 | F73: =D73-E73 -> 0 | G73: 1e-07 | H73: =IF(AND(ISNUMBER(D73),ISNUMBER(E73),ISNUMBER(F73),ISNUMBER(G73)),IF(ABS(F73)<=G73,"PASS","FAIL"),"UNVERIFIED") -> PASS | I73: Scenarios!H52 equals NOPAT + D&A - capex - change in operating NWC.
A74: forecast_base_FY2031_revenue | B74: Approved snapshot | C74: forecast reconciliation — base | D74: =Scenarios!I35 -> 51420.515 | E74: 51420.515 | F74: =D74-E74 -> 0 | G74: 0.1 | H74: =IF(AND(ISNUMBER(D74),ISNUMBER(E74),ISNUMBER(F74),ISNUMBER(G74)),IF(ABS(F74)<=G74,"MATCHES APPROVED","DIFFERS FROM APPROVED"),"UNVERIFIED") -> MATCHES APPROVED | I74: Scenarios!I35
A75: forecast_base_FY2031_derived_operating_income | B75: Approved snapshot | C75: forecast reconciliation — base | D75: =Scenarios!I40 -> 6170.4618 | E75: 6170.4618 | F75: =D75-E75 -> 0 | G75: 0.1 | H75: =IF(AND(ISNUMBER(D75),ISNUMBER(E75),ISNUMBER(F75),ISNUMBER(G75)),IF(ABS(F75)<=G75,"MATCHES APPROVED","DIFFERS FROM APPROVED"),"UNVERIFIED") -> MATCHES APPROVED | I75: Scenarios!I40
A76: forecast_base_FY2031_operating_nwc_proxy | B76: Approved snapshot | C76: forecast reconciliation — base | D76: =Scenarios!I50 -> 5142.0515 | E76: 5142.0515 | F76: =D76-E76 -> 0 | G76: 0.1 | H76: =IF(AND(ISNUMBER(D76),ISNUMBER(E76),ISNUMBER(F76),ISNUMBER(G76)),IF(ABS(F76)<=G76,"MATCHES APPROVED","DIFFERS FROM APPROVED"),"UNVERIFIED") -> MATCHES APPROVED | I76: Scenarios!I50
A77: forecast_base_FY2031_fcff | B77: Approved snapshot | C77: forecast reconciliation — base | D77: =Scenarios!I52 -> 4773.3215 | E77: 4773.3215 | F77: =D77-E77 -> 0 | G77: 0.1 | H77: =IF(AND(ISNUMBER(D77),ISNUMBER(E77),ISNUMBER(F77),ISNUMBER(G77)),IF(ABS(F77)<=G77,"MATCHES APPROVED","DIFFERS FROM APPROVED"),"UNVERIFIED") -> MATCHES APPROVED | I77: Scenarios!I52
A78: fcff_identity_base_FY2031 | B78: Mechanical integrity | C78: FCFF — base | D78: =Scenarios!I52-(Scenarios!I44+Scenarios!I46-Scenarios!I48-Scenarios!I51) -> 0 | E78: 0 | F78: =D78-E78 -> 0 | G78: 1e-07 | H78: =IF(AND(ISNUMBER(D78),ISNUMBER(E78),ISNUMBER(F78),ISNUMBER(G78)),IF(ABS(F78)<=G78,"PASS","FAIL"),"UNVERIFIED") -> PASS | I78: Scenarios!I52 equals NOPAT + D&A - capex - change in operating NWC.
A79: forecast_bull_FY2027_revenue | B79: Approved snapshot | C79: forecast reconciliation — bull | D79: =Scenarios!E60 -> 46629.99 | E79: 46629.99 | F79: =D79-E79 -> 0 | G79: 0.1 | H79: =IF(AND(ISNUMBER(D79),ISNUMBER(E79),ISNUMBER(F79),ISNUMBER(G79)),IF(ABS(F79)<=G79,"MATCHES APPROVED","DIFFERS FROM APPROVED"),"UNVERIFIED") -> MATCHES APPROVED | I79: Scenarios!E60
A80: forecast_bull_FY2027_derived_operating_income | B80: Approved snapshot | C80: forecast reconciliation — bull | D80: =Scenarios!E65 -> 3823.6592 | E80: 3823.6592 | F80: =D80-E80 -> 0 | G80: 0.1 | H80: =IF(AND(ISNUMBER(D80),ISNUMBER(E80),ISNUMBER(F80),ISNUMBER(G80)),IF(ABS(F80)<=G80,"MATCHES APPROVED","DIFFERS FROM APPROVED"),"UNVERIFIED") -> MATCHES APPROVED | I80: Scenarios!E65
A81: forecast_bull_FY2027_operating_nwc_proxy | B81: Approved snapshot | C81: forecast reconciliation — bull | D81: =Scenarios!E75 -> 5036.0389 | E81: 5036.0389 | F81: =D81-E81 -> 0 | G81: 0.1 | H81: =IF(AND(ISNUMBER(D81),ISNUMBER(E81),ISNUMBER(F81),ISNUMBER(G81)),IF(ABS(F81)<=G81,"MATCHES APPROVED","DIFFERS FROM APPROVED"),"UNVERIFIED") -> MATCHES APPROVED | I81: Scenarios!E75
A82: forecast_bull_FY2027_fcff | B82: Approved snapshot | C82: forecast reconciliation — bull | D82: =Scenarios!E77 -> 3445.0218 | E82: 3445.0218 | F82: =D82-E82 -> 0 | G82: 0.1 | H82: =IF(AND(ISNUMBER(D82),ISNUMBER(E82),ISNUMBER(F82),ISNUMBER(G82)),IF(ABS(F82)<=G82,"MATCHES APPROVED","DIFFERS FROM APPROVED"),"UNVERIFIED") -> MATCHES APPROVED | I82: Scenarios!E77
A83: fcff_identity_bull_FY2027 | B83: Mechanical integrity | C83: FCFF — bull | D83: =Scenarios!E77-(Scenarios!E69+Scenarios!E71-Scenarios!E73-Scenarios!E76) -> 0 | E83: 0 | F83: =D83-E83 -> 0 | G83: 1e-07 | H83: =IF(AND(ISNUMBER(D83),ISNUMBER(E83),ISNUMBER(F83),ISNUMBER(G83)),IF(ABS(F83)<=G83,"PASS","FAIL"),"UNVERIFIED") -> PASS | I83: Scenarios!E77 equals NOPAT + D&A - capex - change in operating NWC.
A84: forecast_bull_FY2028_revenue | B84: Approved snapshot | C84: forecast reconciliation — bull | D84: =Scenarios!F60 -> 48495.19 | E84: 48495.19 | F84: =D84-E84 -> 0 | G84: 0.1 | H84: =IF(AND(ISNUMBER(D84),ISNUMBER(E84),ISNUMBER(F84),ISNUMBER(G84)),IF(ABS(F84)<=G84,"MATCHES APPROVED","DIFFERS FROM APPROVED"),"UNVERIFIED") -> MATCHES APPROVED | I84: Scenarios!F60
A85: forecast_bull_FY2028_derived_operating_income | B85: Approved snapshot | C85: forecast reconciliation — bull | D85: =Scenarios!F65 -> 4849.519 | E85: 4849.519 | F85: =D85-E85 -> 0 | G85: 0.1 | H85: =IF(AND(ISNUMBER(D85),ISNUMBER(E85),ISNUMBER(F85),ISNUMBER(G85)),IF(ABS(F85)<=G85,"MATCHES APPROVED","DIFFERS FROM APPROVED"),"UNVERIFIED") -> MATCHES APPROVED | I85: Scenarios!F65
A86: forecast_bull_FY2028_operating_nwc_proxy | B86: Approved snapshot | C86: forecast reconciliation — bull | D86: =Scenarios!F75 -> 5043.4997 | E86: 5043.4997 | F86: =D86-E86 -> 0 | G86: 0.1 | H86: =IF(AND(ISNUMBER(D86),ISNUMBER(E86),ISNUMBER(F86),ISNUMBER(G86)),IF(ABS(F86)<=G86,"MATCHES APPROVED","DIFFERS FROM APPROVED"),"UNVERIFIED") -> MATCHES APPROVED | I86: Scenarios!F75
A87: forecast_bull_FY2028_fcff | B87: Approved snapshot | C87: forecast reconciliation — bull | D87: =Scenarios!F77 -> 3726.6688 | E87: 3726.6688 | F87: =D87-E87 -> 0 | G87: 0.1 | H87: =IF(AND(ISNUMBER(D87),ISNUMBER(E87),ISNUMBER(F87),ISNUMBER(G87)),IF(ABS(F87)<=G87,"MATCHES APPROVED","DIFFERS FROM APPROVED"),"UNVERIFIED") -> MATCHES APPROVED | I87: Scenarios!F77
A88: fcff_identity_bull_FY2028 | B88: Mechanical integrity | C88: FCFF — bull | D88: =Scenarios!F77-(Scenarios!F69+Scenarios!F71-Scenarios!F73-Scenarios!F76) -> 0 | E88: 0 | F88: =D88-E88 -> 0 | G88: 1e-07 | H88: =IF(AND(ISNUMBER(D88),ISNUMBER(E88),ISNUMBER(F88),ISNUMBER(G88)),IF(ABS(F88)<=G88,"PASS","FAIL"),"UNVERIFIED") -> PASS | I88: Scenarios!F77 equals NOPAT + D&A - capex - change in operating NWC.
A89: forecast_bull_FY2029_revenue | B89: Approved snapshot | C89: forecast reconciliation — bull | D89: =Scenarios!G60 -> 50919.949 | E89: 50919.949 | F89: =D89-E89 -> 0 | G89: 0.1 | H89: =IF(AND(ISNUMBER(D89),ISNUMBER(E89),ISNUMBER(F89),ISNUMBER(G89)),IF(ABS(F89)<=G89,"MATCHES APPROVED","DIFFERS FROM APPROVED"),"UNVERIFIED") -> MATCHES APPROVED | I89: Scenarios!G60
A90: forecast_bull_FY2029_derived_operating_income | B90: Approved snapshot | C90: forecast reconciliation — bull | D90: =Scenarios!G65 -> 6110.3939 | E90: 6110.3939 | F90: =D90-E90 -> 0 | G90: 0.1 | H90: =IF(AND(ISNUMBER(D90),ISNUMBER(E90),ISNUMBER(F90),ISNUMBER(G90)),IF(ABS(F90)<=G90,"MATCHES APPROVED","DIFFERS FROM APPROVED"),"UNVERIFIED") -> MATCHES APPROVED | I90: Scenarios!G65
A91: forecast_bull_FY2029_operating_nwc_proxy | B91: Approved snapshot | C91: forecast reconciliation — bull | D91: =Scenarios!G75 -> 5091.9949 | E91: 5091.9949 | F91: =D91-E91 -> 0 | G91: 0.1 | H91: =IF(AND(ISNUMBER(D91),ISNUMBER(E91),ISNUMBER(F91),ISNUMBER(G91)),IF(ABS(F91)<=G91,"MATCHES APPROVED","DIFFERS FROM APPROVED"),"UNVERIFIED") -> MATCHES APPROVED | I91: Scenarios!G75
A92: forecast_bull_FY2029_fcff | B92: Approved snapshot | C92: forecast reconciliation — bull | D92: =Scenarios!G77 -> 4625.9561 | E92: 4625.9561 | F92: =D92-E92 -> 0 | G92: 0.1 | H92: =IF(AND(ISNUMBER(D92),ISNUMBER(E92),ISNUMBER(F92),ISNUMBER(G92)),IF(ABS(F92)<=G92,"MATCHES APPROVED","DIFFERS FROM APPROVED"),"UNVERIFIED") -> MATCHES APPROVED | I92: Scenarios!G77
A93: fcff_identity_bull_FY2029 | B93: Mechanical integrity | C93: FCFF — bull | D93: =Scenarios!G77-(Scenarios!G69+Scenarios!G71-Scenarios!G73-Scenarios!G76) -> 0 | E93: 0 | F93: =D93-E93 -> 0 | G93: 1e-07 | H93: =IF(AND(ISNUMBER(D93),ISNUMBER(E93),ISNUMBER(F93),ISNUMBER(G93)),IF(ABS(F93)<=G93,"PASS","FAIL"),"UNVERIFIED") -> PASS | I93: Scenarios!G77 equals NOPAT + D&A - capex - change in operating NWC.
A94: forecast_bull_FY2030_revenue | B94: Approved snapshot | C94: forecast reconciliation — bull | D94: =Scenarios!H60 -> 53465.947 | E94: 53465.947 | F94: =D94-E94 -> 0 | G94: 0.1 | H94: =IF(AND(ISNUMBER(D94),ISNUMBER(E94),ISNUMBER(F94),ISNUMBER(G94)),IF(ABS(F94)<=G94,"MATCHES APPROVED","DIFFERS FROM APPROVED"),"UNVERIFIED") -> MATCHES APPROVED | I94: Scenarios!H60
A95: forecast_bull_FY2030_derived_operating_income | B95: Approved snapshot | C95: forecast reconciliation — bull | D95: =Scenarios!H65 -> 7110.9709 | E95: 7110.9709 | F95: =D95-E95 -> 0 | G95: 0.1 | H95: =IF(AND(ISNUMBER(D95),ISNUMBER(E95),ISNUMBER(F95),ISNUMBER(G95)),IF(ABS(F95)<=G95,"MATCHES APPROVED","DIFFERS FROM APPROVED"),"UNVERIFIED") -> MATCHES APPROVED | I95: Scenarios!H65
A96: forecast_bull_FY2030_operating_nwc_proxy | B96: Approved snapshot | C96: forecast reconciliation — bull | D96: =Scenarios!H75 -> 5186.1968 | E96: 5186.1968 | F96: =D96-E96 -> 0 | G96: 0.1 | H96: =IF(AND(ISNUMBER(D96),ISNUMBER(E96),ISNUMBER(F96),ISNUMBER(G96)),IF(ABS(F96)<=G96,"MATCHES APPROVED","DIFFERS FROM APPROVED"),"UNVERIFIED") -> MATCHES APPROVED | I96: Scenarios!H75
A97: forecast_bull_FY2030_fcff | B97: Approved snapshot | C97: forecast reconciliation — bull | D97: =Scenarios!H77 -> 5416.5332 | E97: 5416.5332 | F97: =D97-E97 -> 0 | G97: 0.1 | H97: =IF(AND(ISNUMBER(D97),ISNUMBER(E97),ISNUMBER(F97),ISNUMBER(G97)),IF(ABS(F97)<=G97,"MATCHES APPROVED","DIFFERS FROM APPROVED"),"UNVERIFIED") -> MATCHES APPROVED | I97: Scenarios!H77
A98: fcff_identity_bull_FY2030 | B98: Mechanical integrity | C98: FCFF — bull | D98: =Scenarios!H77-(Scenarios!H69+Scenarios!H71-Scenarios!H73-Scenarios!H76) -> 0 | E98: 0 | F98: =D98-E98 -> 0 | G98: 1e-07 | H98: =IF(AND(ISNUMBER(D98),ISNUMBER(E98),ISNUMBER(F98),ISNUMBER(G98)),IF(ABS(F98)<=G98,"PASS","FAIL"),"UNVERIFIED") -> PASS | I98: Scenarios!H77 equals NOPAT + D&A - capex - change in operating NWC.
A99: forecast_bull_FY2031_revenue | B99: Approved snapshot | C99: forecast reconciliation — bull | D99: =Scenarios!I60 -> 55337.255 | E99: 55337.255 | F99: =D99-E99 -> 0 | G99: 0.1 | H99: =IF(AND(ISNUMBER(D99),ISNUMBER(E99),ISNUMBER(F99),ISNUMBER(G99)),IF(ABS(F99)<=G99,"MATCHES APPROVED","DIFFERS FROM APPROVED"),"UNVERIFIED") -> MATCHES APPROVED | I99: Scenarios!I60
A100: forecast_bull_FY2031_derived_operating_income | B100: Approved snapshot | C100: forecast reconciliation — bull | D100: =Scenarios!I65 -> 7747.2157 | E100: 7747.2157 | F100: =D100-E100 -> 0 | G100: 0.1 | H100: =IF(AND(ISNUMBER(D100),ISNUMBER(E100),ISNUMBER(F100),ISNUMBER(G100)),IF(ABS(F100)<=G100,"MATCHES APPROVED","DIFFERS FROM APPROVED"),"UNVERIFIED") -> MATCHES APPROVED | I100: Scenarios!I65
A101: forecast_bull_FY2031_operating_nwc_proxy | B101: Approved snapshot | C101: forecast reconciliation — bull | D101: =Scenarios!I75 -> 5257.0392 | E101: 5257.0392 | F101: =D101-E101 -> 0 | G101: 0.1 | H101: =IF(AND(ISNUMBER(D101),ISNUMBER(E101),ISNUMBER(F101),ISNUMBER(G101)),IF(ABS(F101)<=G101,"MATCHES APPROVED","DIFFERS FROM APPROVED"),"UNVERIFIED") -> MATCHES APPROVED | I101: Scenarios!I75
A102: forecast_bull_FY2031_fcff | B102: Approved snapshot | C102: forecast reconciliation — bull | D102: =Scenarios!I77 -> 5994.1207 | E102: 5994.1207 | F102: =D102-E102 -> 0 | G102: 0.1 | H102: =IF(AND(ISNUMBER(D102),ISNUMBER(E102),ISNUMBER(F102),ISNUMBER(G102)),IF(ABS(F102)<=G102,"MATCHES APPROVED","DIFFERS FROM APPROVED"),"UNVERIFIED") -> MATCHES APPROVED | I102: Scenarios!I77
A103: fcff_identity_bull_FY2031 | B103: Mechanical integrity | C103: FCFF — bull | D103: =Scenarios!I77-(Scenarios!I69+Scenarios!I71-Scenarios!I73-Scenarios!I76) -> 0 | E103: 0 | F103: =D103-E103 -> 0 | G103: 1e-07 | H103: =IF(AND(ISNUMBER(D103),ISNUMBER(E103),ISNUMBER(F103),ISNUMBER(G103)),IF(ABS(F103)<=G103,"PASS","FAIL"),"UNVERIFIED") -> PASS | I103: Scenarios!I77 equals NOPAT + D&A - capex - change in operating NWC.
...
